Workbook

Sheet Cover & Method
A1: ISO/IEC 27001:2022 Gap Analysis
A2: Aldridge Financial Technologies | AFT-ISMS-GAP-01 | Version 2.0 | 9 September 2026 | Classification: Confidential
A5: ENGAGEMENT
A6: Assessed entity | B6: Aldridge Financial Technologies, Inc. and Aldridge Financial Technologies (UK) Ltd
A7: Standard | B7: ISO/IEC 27001:2022, including Annex A (93 controls) and management system clauses 4 to 10
A8: Assessment date | B8: September 2026
A9: Assessed by | B9: Security Governance (Chidi Eze), reviewed by the Chief Information Security Officer
A10: Certification target | B10: Stage 1 audit Q2 2027
A11: Basis of assessment | B11: Document review, control walkthroughs, system inspection and interview. No independent testing of operating effectiveness was performed; this is a gap analysis, not an audit.
A12: Source of record | B12: AFT-CTX-01 Organisation Context Pack v1.0
A14: SCOPE STATEMENT (DRAFT, NOT YET APPROVED)
B15: The information security management system supporting the design, development, operation and support of the Aldridge Pay, Aldridge Credit and Aldridge Ledger platforms, and the corporate functions that support them, delivered from AWS regions us-east-1, us-west-2 and eu-west-2 and from the company's offices in Austin, Texas and London, United Kingdom.
A17: IMPLEMENTATION STATUS SCALE
A18: Implemented | B18: Control is designed appropriately, operating, and evidenced.
A19: Partially implemented | B19: Control exists but has a design or operating deficiency, or lacks evidence.
A20: Not implemented | B20: Control is absent or exists only as intent.
A21: Not applicable | B21: Control does not apply. Justification required in the Statement of Applicability.
A23: MATURITY SCALE
A24: 0 — Non-existent | B24: No recognisable activity.
A25: 1 — Initial | B25: Ad hoc, dependent on individuals, undocumented.
A26: 2 — Repeatable | B26: Consistent in practice but not formally defined.
A27: 3 — Defined | B27: Documented, communicated, and performed consistently.
A28: 4 — Managed | B28: Measured, monitored, and reported with metrics.
A29: 5 — Optimised | B29: Continuously improved against measured outcomes.
A30: Certification threshold | B30: Maturity 3 is the minimum for a control to be certifiable. A gap is raised for any applicable control below 3.
A32: GAP PRIORITY
A33: P1 | B33: Prerequisite for audit readiness — the ISMS cannot be assessed without it. Target 31 January 2027.
A34: P2 | B34: Would generate a major nonconformity at Stage 2. Target 31 March 2027.
A35: P3 | B35: Would generate a minor nonconformity or an observation. Target 30 June 2027.
A36: P4 | B36: Improvement opportunity, not certification-blocking. Post-certification.
A38: IMPORTANT LIMITATION
B39: Annex A is a set of possible controls, not the certification requirement. Certification is granted against clauses 4 to 10. A company can implement every Annex A control and still fail. The 'Clause Gaps' tab is therefore the more consequential of the two registers and should be read first.

Sheet Summary
A1: Assessment Summary
A2: All figures are formulas driven by the 'Annex A Register' and 'Clause Gaps' tabs. Edit those tabs and these update.
A4: ANNEX A — IMPLEMENTATION STATUS
A5: Status | B5: Count | C5: % of applicable
A6: Implemented | B6: =COUNTIF('Annex A Register'!$G$4:$G$96,A6) -> 46 | C6: =IFERROR(B6/$B$11,0) -> 0.5
A7: Partially implemented | B7: =COUNTIF('Annex A Register'!$G$4:$G$96,A7) -> 43 | C7: =IFERROR(B7/$B$11,0) -> 0.4673913
A8: Not implemented | B8: =COUNTIF('Annex A Register'!$G$4:$G$96,A8) -> 3 | C8: =IFERROR(B8/$B$11,0) -> 0.032608696
A9: Not applicable | B9: =COUNTIF('Annex A Register'!$G$4:$G$96,A9) -> 1
A10: Total controls | B10: =COUNTA('Annex A Register'!$A$4:$A$96) -> 93
A11: Applicable controls | B11: =COUNTIF('Annex A Register'!$D$4:$D$96,"Yes") -> 92
A12: Controls with a gap | B12: =COUNTIFS('Annex A Register'!$D$4:$D$96,"Yes",'Annex A Register'!$I$4:$I$96,"<3") -> 46
A13: Conformance rate (applicable at maturity 3+) | B13: =IFERROR((B11-B12)/B11,0) -> 0.5
A15: ANNEX A — GAPS BY THEME
A16: Theme | B16: Controls | C16: Gaps | D16: Gap rate
A17: Organisational | B17: =COUNTIF('Annex A Register'!$C$4:$C$96,A17) -> 37 | C17: =COUNTIFS('Annex A Register'!$C$4:$C$96,A17,'Annex A Register'!$D$4:$D$96,"Yes",'Annex A Register'!$I$4:$I$96,"<3") -> 22 | D17: =IFERROR(C17/B17,0) -> 0.59459459
A18: People | B18: =COUNTIF('Annex A Register'!$C$4:$C$96,A18) -> 8 | C18: =COUNTIFS('Annex A Register'!$C$4:$C$96,A18,'Annex A Register'!$D$4:$D$96,"Yes",'Annex A Register'!$I$4:$I$96,"<3") -> 2 | D18: =IFERROR(C18/B18,0) -> 0.25
A19: Physical | B19: =COUNTIF('Annex A Register'!$C$4:$C$96,A19) -> 14 | C19: =COUNTIFS('Annex A Register'!$C$4:$C$96,A19,'Annex A Register'!$D$4:$D$96,"Yes",'Annex A Register'!$I$4:$I$96,"<3") -> 5 | D19: =IFERROR(C19/B19,0) -> 0.35714286
A20: Technological | B20: =COUNTIF('Annex A Register'!$C$4:$C$96,A20) -> 34 | C20: =COUNTIFS('Annex A Register'!$C$4:$C$96,A20,'Annex A Register'!$D$4:$D$96,"Yes",'Annex A Register'!$I$4:$I$96,"<3") -> 17 | D20: =IFERROR(C20/B20,0) -> 0.5
A23: GAPS BY PRIORITY
A24: Priority | B24: Annex A gaps | C24: Clause gaps | D24: Total
A25: P1 | B25: =COUNTIF('Annex A Register'!$K$4:$K$96,A25) -> 3 | C25: =COUNTIF('Clause Gaps'!$G$4:$G$28,A25) -> 14 | D25: =B25+C25 -> 17
A26: P2 | B26: =COUNTIF('Annex A Register'!$K$4:$K$96,A26) -> 29 | C26: =COUNTIF('Clause Gaps'!$G$4:$G$28,A26) -> 8 | D26: =B26+C26 -> 37
A27: P3 | B27: =COUNTIF('Annex A Register'!$K$4:$K$96,A27) -> 12 | C27: =COUNTIF('Clause Gaps'!$G$4:$G$28,A27) -> 2 | D27: =B27+C27 -> 14
A28: P4 | B28: =COUNTIF('Annex A Register'!$K$4:$K$96,A28) -> 2 | C28: =COUNTIF('Clause Gaps'!$G$4:$G$28,A28) -> 0 | D28: =B28+C28 -> 2
A29: Total | B29: =SUM(B25:B28) -> 46 | C29: =SUM(C25:C28) -> 24 | D29: =SUM(D25:D28) -> 70
A31: MANAGEMENT SYSTEM CLAUSES 4–10
A32: Status | B32: Count | C32: % of clauses
A33: Implemented | B33: =COUNTIF('Clause Gaps'!$E$4:$E$28,A33) -> 1 | C33: =IFERROR(B33/$B$36,0) -> 0.04
A34: Partially implemented | B34: =COUNTIF('Clause Gaps'!$E$4:$E$28,A34) -> 14 | C34: =IFERROR(B34/$B$36,0) -> 0.56
A35: Not implemented | B35: =COUNTIF('Clause Gaps'!$E$4:$E$28,A35) -> 10 | C35: =IFERROR(B35/$B$36,0) -> 0.4
A36: Total clause requirements | B36: =COUNTA('Clause Gaps'!$A$4:$A$28) -> 25
A38: READING THE NUMBERS
A39: The Annex A conformance rate is respectable for a company that has never run an ISMS, and reflects control maturity inherited from PCI DSS and SOC 2. The clause 4-10 position is the opposite and is the real finding: the management system that ISO/IEC 27001 actually certifies does not yet exist. Closing Annex A gaps without building the management system would not produce a certifiable organisation.

Sheet Annex A Register
A1: Annex A Control Register — all 93 controls
A2: Every assessment is supported by the evidence named in column F. Effort is internal person-days; cost is indicative external spend.
A3: Ref | B3: Control title | C3: Theme | D3: Applicable | E3: Current state | F3: Evidence reviewed | G3: Status | H3: Design / operating | I3: Maturity | J3: Gap description | K3: Priority | L3: Remediation action | M3: Effort (days) | N3: External cost (USD) | O3: Predecessor | P3: Owner | Q3: Target date | R3: Ref (CTX)
A4: A.5.1 | B4: Policies for information security | C4: Organisational | D4: Yes | E4: Four Tier 2 policies issued and current (POL-01 to POL-04). Secure development, cryptography, business continuity and TPRM policies also issued. No Tier 1 apex Information Security Policy exists. | F4: Policy library index reviewed 2 Sep 2026 (9 documents). No Tier 1 policy located. Interview: Head of Security Governance. | G4: Partially implemented | I4: 2 | J4: There is no top-level Information Security Policy establishing the ISMS, management commitment and the policy framework. AFT-ISMS-POL-05 is listed in the document register but has never been written. Policies are not linked to a Statement of Applicability. | K4: P1 | L4: Draft, approve and publish AFT-ISMS-POL-05 Information Security Policy at Tier 1, signed by the CEO. Map every Tier 2 policy and standard to it and to the SoA. Establish an annual policy review calendar. | M4: 8 | N4: — | O4: — | P4: Helen Achebe-Ward | Q4: 31 Jan 2027 | R4: POL-05
A5: A.5.2 | B5: Information security roles and responsibilities | C5: Organisational | D5: Yes | E5: Roles are described within individual policies. Security function is established with named leaders. No consolidated RACI across the ISMS. | F5: POL-01 to POL-09 role sections reviewed. No consolidated RACI produced on request. | G5: Partially implemented | I5: 2 | J5: Responsibilities are distributed across policy documents rather than defined once and maintained. No documented allocation of ISMS-specific responsibilities (risk owner, control owner, ISMS manager). | K5: P2 | L5: Produce a single ISMS roles and responsibilities matrix covering all Annex A control owners and clause responsibilities. Ratify at the Executive Risk Committee and reference it from POL-05. | M5: 6 | N5: — | O5: 5.2 | P5: Chidi Eze | Q5: 31 Mar 2027
A6: A.5.3 | B6: Segregation of duties | C6: Organisational | D6: Yes | E6: Principle stated in POL-03 section 3. Conflicting access is refused at request stage on reviewer judgement. Change and deployment duties are separated in CI/CD. | F6: Okta group configuration inspected. No SoD matrix produced on request. Interview: Head of Identity and Access. | G6: Partially implemented | I6: 2 | J6: No documented segregation of duties matrix defining which role combinations are conflicting. Detection relies on the approver recognising a conflict rather than on a defined rule set. | K6: P2 | L6: Build a segregation of duties conflict matrix for finance, payments, lending and platform roles. Encode the rules in Okta and the access request workflow so conflicts are blocked, not judged. | M6: 12 | N6: — | O6: A.5.9 | P6: Ruth Nakamura | Q6: 31 Mar 2027
A7: A.5.4 | B7: Management responsibilities | C7: Organisational | D7: Yes | E7: Executive Risk Committee meets monthly and receives security reporting. Security Steering Group meets fortnightly. | F7: ERC terms of reference and 6 months of minutes reviewed (Mar-Aug 2026). No ISMS standing item present. | G7: Partially implemented | I7: 2 | J7: Management direction is exercised in practice but not documented as an ISMS obligation. No evidence that management requires all personnel to apply information security in accordance with established policies. | K7: P2 | L7: Document management responsibilities in POL-05. Add a standing ISMS agenda item to the ERC with recorded decisions and actions. | M7: 3 | N7: — | O7: 5.2 | P7: Helen Achebe-Ward | Q7: 31 Mar 2027
A8: A.5.5 | B8: Contact with authorities | C8: Organisational | D8: Yes | E8: POL-02 defines the notification matrix and routes for the ICO, FCA, payment brands, acquirer and state regulators. Named contacts held by Legal and the DPO. | F8: POL-02 s7 notification matrix reviewed. Contact list for ICO, FCA, acquirer inspected, dated Jul 2026. | G8: Implemented | H8: Design and operation adequate | I8: 3
A9: A.5.6 | B9: Contact with special interest groups | C9: Organisational | D9: Yes | E9: SOC analysts hold personal memberships of FS-ISAC and regional security forums. No organisational membership or defined participation. | F9: Interview: Head of Security Operations. No organisational membership records produced. | G9: Partially implemented | I9: 2 | J9: Participation is individual and informal. If the analysts concerned left, the contact would be lost. No process for disseminating what is learned. | K9: P3 | L9: Take out organisational FS-ISAC membership. Define named representatives and deputies, and a route for intelligence received to reach the SOC and the Security Steering Group. | M9: 2 | N9: 8000 | O9: — | P9: Tomas Vidal | Q9: 30 Jun 2027
A10: A.5.7 | B10: Threat intelligence | C10: Organisational | D10: Yes | E10: The SOC consumes vendor feeds bundled with CrowdStrike and Wiz. No defined intelligence requirements, no strategic or tactical intelligence process, no dissemination. | F10: Interview: SOC lead analyst. No intelligence requirements document exists. CrowdStrike and Wiz feed configuration inspected. | G10: Not implemented | H10: Design absent | I10: 1 | J10: Threat intelligence is a by-product of tooling rather than a control. There are no documented intelligence requirements, no assessment of relevance to Aldridge's threat profile, and no linkage into risk assessment or control selection. | K10: P2 | L10: Define priority intelligence requirements based on the payments and lending threat landscape. Formalise collection sources, analysis cadence and dissemination to the SOC, engineering and the Security Steering Group. Feed intelligence into the risk assessment cycle. | M10: 20 | N10: 60000 | O10: — | P10: Tomas Vidal | Q10: 31 Mar 2027 | R10: W-05
A11: A.5.8 | B11: Information security in project management | C11: Organisational | D11: Yes | E11: Security is engaged on large initiatives by relationship rather than by process. No security gate in the delivery lifecycle. | F11: Delivery lifecycle checklist reviewed. Sample of 6 projects initiated 2026: security engagement recorded in 2. | G11: Partially implemented | I11: 2 | J11: Security involvement depends on whether a team thinks to ask. Smaller projects and product changes proceed without any security consideration being recorded. | K11: P2 | L11: Introduce a mandatory security assessment step at project initiation, sized by risk. Add security sign-off to the delivery lifecycle checklist and record it in Jira. | M11: 10 | N11: — | O11: 5.2 | P11: Marcus Lindqvist | Q11: 31 Mar 2027
A12: A.5.9 | B12: Inventory of information and other associated assets | C12: Organisational | D12: Yes | E12: Infrastructure assets are well inventoried through Wiz and Terraform state. Information assets are catalogued for the CDE and secure data zone. Approximately 40 SaaS applications identified by CASB in August 2026 are not registered. | F12: Asset register export 1 Sep 2026 (1,247 entries). CASB discovery report Aug 2026 reconciled: 40 applications unmatched. | G12: Partially implemented | H12: Design adequate; operation deficient (inventory not maintained) | I12: 2 | J12: The asset inventory is materially incomplete. Unregistered SaaS applications have no recorded owner, classification, or assessment, which means neither the risk assessment nor the ISMS scope can be relied upon. | K12: P1 | L12: Reconcile the CASB discovery output against the asset register. Assign an owner and classification to every application, or decommission it. Establish monthly CASB-to-register reconciliation as a standing control. | M12: 30 | N12: — | O12: — | P12: Claire Bennett | Q12: 31 Jan 2027 | R12: W-04
A13: A.5.10 | B13: Acceptable use of information and other associated assets | C13: Organisational | D13: Yes | E13: POL-01 v2.1 issued and current, covering endpoints, communications, cloud, generative AI and remote working. Acknowledged at onboarding. | F13: POL-01 v2.1 reviewed. Acknowledgement records sampled, 20 of 20 present. | G13: Implemented | H13: Design and operation adequate | I13: 4
A14: A.5.11 | B14: Return of assets | C14: Organisational | D14: Yes | E14: PRO-03 requires recovery of devices and credentials on or before the final working day. Tracked in the HRIS offboarding workflow. | F14: PRO-03 reviewed. Sample of 10 leavers Q2 2026: asset recovery evidenced in 10. | G14: Implemented | H14: Design and operation adequate | I14: 3
A15: A.5.12 | B15: Classification of information | C15: Organisational | D15: Yes | E15: POL-04 v2.0 defines four levels with owner accountability and an aggregation rule. Applied consistently in the CDE and secure data zone. | F15: POL-04 v2.0 reviewed. Data catalogue inspected for CDE and secure data zone. | G15: Implemented | H15: Design and operation adequate | I15: 3
A16: A.5.13 | B16: Labelling of information | C16: Organisational | D16: Yes | E16: Sensitivity labelling deployed in Google Workspace. Document footers required by POL-04. Adoption measured at approximately 60% of eligible documents. | F16: Google Workspace labelling configuration inspected. Adoption report 31 Aug 2026: 61% of eligible documents labelled. | G16: Partially implemented | H16: Design adequate; operation deficient (adoption at 61%) | I16: 2 | J16: Labelling is required by policy but not enforced or consistently applied. Unlabelled Confidential material circulates, which undermines the data loss prevention rules that depend on labels. | K16: P3 | L16: Enable default labelling and mandatory label prompts in Google Workspace. Run a labelling remediation campaign on existing shared drives. Report adoption monthly until above 95%. | M16: 12 | N16: — | O16: A.5.9 | P16: Claire Bennett | Q16: 30 Jun 2027
A17: A.5.14 | B17: Information transfer | C17: Organisational | D17: Yes | E17: POL-04 section 6.2 prohibits email for Restricted data and mandates the secure transfer platform. Managed links with expiry for Confidential data. NDAs required before external sharing. | F17: POL-04 s6.2 reviewed. Secure transfer platform configuration inspected. Sharing link audit sampled. | G17: Implemented | H17: Design and operation adequate | I17: 3
A18: A.5.15 | B18: Access control | C18: Organisational | D18: Yes | E18: POL-03 v2.2 establishes least privilege, need to know, deny by default and time-bound privilege. Enforced through Okta and CyberArk. | F18: POL-03 v2.2 reviewed. Okta policy configuration inspected. | G18: Implemented | H18: Design and operation adequate | I18: 4
A19: A.5.16 | B19: Identity management | C19: Organisational | D19: Yes | E19: Okta is the authoritative identity provider. Unique identities for all workers. Service accounts have named owners and non-interactive login only. | F19: Okta directory inspected 3 Sep 2026: 610 active identities, 0 shared interactive accounts, 84 service accounts all with named owner. | G19: Implemented | H19: Design and operation adequate | I19: 4
A20: A.5.17 | B20: Authentication information | C20: Organisational | D20: Yes | E20: MFA universal. Phishing-resistant FIDO2 mandatory for privileged access. Credentials held in HashiCorp Vault. Breached-password screening at set and at use. | F20: Okta authentication policy inspected. Vault configuration reviewed. FIDO2 enrolment: 100% of 41 privileged holders. | G20: Implemented | H20: Design and operation adequate | I20: 4
A21: A.5.18 | B21: Access rights | C21: Organisational | D21: Yes | E21: Quarterly recertification for all entitlements, monthly for privileged and CDE access. Automatic revocation of unconfirmed access. Leaver revocation within four hours, evidenced. | F21: Q2 2026 recertification campaign records reviewed: 100% completion, 214 entitlements revoked. Leaver revocation sample of 15: all within 4 hours. | G21: Implemented | H21: Design and operation adequate | I21: 4
A22: A.5.19 | B22: Information security in supplier relationships | C22: Organisational | D22: Yes | E22: POL-09 v1.3 requires assessment before onboarding. Procurement gatekeeps new supplier engagement. Assessment is performed at onboarding for all Tier 1 and Tier 2 suppliers. | F22: POL-09 v1.3 reviewed. Supplier onboarding records sampled, 8 of 8 assessed at onboarding. No offboarding security requirements located. | G22: Partially implemented | I22: 2 | J22: The process is defined for new suppliers but there is no documented approach to managing security across the supplier lifecycle, and no exit or termination security requirements. | K22: P2 | L22: Extend POL-09 to cover the full supplier lifecycle including offboarding, data return and destruction. Define security requirements for supplier exit and test them on the next termination. | M22: 8 | N22: — | O22: — | P22: Elena Petrova | Q22: 31 Mar 2027 | R22: W-08
A23: A.5.20 | B23: Addressing information security within supplier agreements | C23: Organisational | D23: Yes | E23: Standard security schedule applied to contracts executed since 2023, covering incident notification within 24 hours, audit rights and data handling. | F23: Contract register reviewed. 8 of 34 Tier 1/2 agreements lack the 2023 security schedule; list obtained from Legal. | G23: Partially implemented | H23: Design adequate for new contracts; legacy population outside scope of the design | I23: 2 | J23: Contracts predating 2023 do not carry the standard security schedule. Eight Tier 1 and Tier 2 suppliers, including Northgate Analytics, are on legacy paper with weaker or absent security terms. | K23: P2 | L23: Identify all Tier 1 and Tier 2 agreements lacking the current security schedule. Prioritise renegotiation at next renewal, and seek immediate amendment for Tier 1 suppliers on the critical path. | M23: 15 | N23: 25000 | O23: A.5.19 | P23: Jonathan Reyes | Q23: 31 Mar 2027 | R23: W-08
A24: A.5.21 | B24: Managing information security in the ICT supply chain | C24: Organisational | D24: Yes | E24: No process exists. Subcontractors and fourth parties used by suppliers are not identified, disclosed or assessed. | F24: Interview: Head of Procurement. No subcontractor register exists. TPRM questionnaire reviewed: no disclosure question present at assessment date. | G24: Not implemented | H24: Design absent | I24: 1 | J24: Aldridge has no visibility of the onward supply chain. It cannot answer where its data physically resides beyond the first tier, which is a direct exposure given Restricted data is shared with Tier 1 suppliers. | K24: P2 | L24: Add mandatory subcontractor disclosure to the TPRM questionnaire and to contract terms, with a notification obligation before any change. Map the fourth parties of all Tier 1 suppliers. | M24: 15 | N24: — | O24: A.5.19 | P24: Elena Petrova | Q24: 31 Mar 2027
A25: A.5.22 | B25: Monitoring, review and change management of supplier services | C25: Organisational | D25: Yes | E25: Reassessment is required annually for Tier 1 and Tier 2 by POL-09. Eleven of thirty-four Tier 1 and Tier 2 suppliers are overdue. Northgate Analytics (V-01) was last assessed in October 2024. | F25: Reassessment tracker reviewed 2 Sep 2026: 11 of 34 Tier 1/2 overdue. Northgate last assessment dated Oct 2024. | G25: Partially implemented | H25: Design adequate; operation deficient (reassessment not performed) | I25: 2 | J25: The reassessment obligation is defined but not performed. A critical-path supplier handling Restricted cardholder data has not been assessed for 23 months. There is no ongoing monitoring of supplier performance against security terms between assessments. | K25: P2 | L25: Clear the reassessment backlog, Tier 1 first, by 31 January 2027. Implement continuous supplier monitoring for Tier 1. Add reassessment due dates to the procurement system with automated escalation to the CISO at 30 days overdue. | M25: 35 | N25: — | O25: A.5.19 | P25: Elena Petrova | Q25: 31 Mar 2027 | R25: W-08
A26: A.5.23 | B26: Information security for use of cloud services | C26: Organisational | D26: Yes | E26: AWS is well governed with landing zones, guardrails, Wiz posture management and Terraform. SaaS acquisition is governed by POL-01 section 3.6 but not enforced technically. Approximately 40 unregistered SaaS applications are in use. | F26: AWS landing zone and Wiz configuration inspected. CASB report Aug 2026: 40 unregistered applications, 11 handling apparent Confidential content. | G26: Partially implemented | I26: 2 | J26: Cloud governance is strong for infrastructure and weak for software as a service. Unregistered applications may be processing Confidential or Restricted data with no assessment, no contract and no exit provision, and they fall outside the declared ISMS scope. | K26: P1 | L26: Triage the 40 discovered applications by data classification. Block or sanction each one. Route SaaS procurement through Okta and Procurement so that acquisition without assessment is not technically possible. | M26: 25 | N26: 30000 | O26: A.5.9 | P26: Sanjay Mehta | Q26: 31 Jan 2027 | R26: W-04
A27: A.5.24 | B27: Information security incident management planning and preparation | C27: Organisational | D27: Yes | E27: POL-02 v3.0 and PLN-01 runbooks issued. Named Incident Commanders with deputies. DFIR retainer in place. Two tabletop exercises completed in 2026, one with executive participation. | F27: POL-02 v3.0 and PLN-01 runbooks reviewed. DFIR retainer agreement inspected. Exercise reports Feb and Jul 2026 reviewed. | G27: Implemented | H27: Design and operation adequate | I27: 4
A28: A.5.25 | B28: Assessment and decision on information security events | C28: Organisational | D28: Yes | E28: Four-tier severity model with documented triage criteria. Provisional severity assigned at triage and reassessed as facts change. | F28: Triage criteria reviewed. Sample of 30 events Q2 2026: severity assigned in 30, reassessed in 4. | G28: Implemented | H28: Design and operation adequate | I28: 4
A29: A.5.26 | B29: Response to information security incidents | C29: Organisational | D29: Yes | E29: Six-phase lifecycle aligned to NIST SP 800-61. Incident Commander holds decision authority. Response evidenced across 2026 incidents. | F29: Incident records for 3 S2 and 1 S3 incident in 2026 reviewed end to end. | G29: Implemented | H29: Design and operation adequate | I29: 4
A30: A.5.27 | B30: Learning from information security incidents | C30: Organisational | D30: Yes | E30: Blameless post-incident review mandatory for S1 and S2. Actions assigned with owners and due dates and tracked to closure at the ERC. | F30: Post-incident review reports for 3 incidents reviewed. Action tracker inspected: 14 of 17 actions closed. | G30: Implemented | H30: Design and operation adequate | I30: 3
A31: A.5.28 | B31: Collection of evidence | C31: Organisational | D31: Yes | E31: STD-08 Digital Evidence Handling Standard issued. Chain of custody documented. Forensic imaging performed before rebuild. External DFIR provider retained. | F31: STD-08 reviewed. Chain of custody records for the Apr 2026 incident inspected. | G31: Implemented | H31: Design and operation adequate | I31: 3
A32: A.5.29 | B32: Information security during disruption | C32: Organisational | D32: Yes | E32: PLN-03 issued covering continuity and recovery. Component-level failover tested quarterly. No end-to-end test since March 2025. | F32: POL-08 and PLN-03 reviewed. Last full exercise report dated Mar 2025. | G32: Partially implemented | I32: 2 | J32: Continuity arrangements are documented but unproven at whole-service level. The recovery time objectives stated for A-01, A-02, A-10, A-11, A-12 and A-15 have not been validated in an integrated test. | K32: P2 | L32: Run a full end-to-end disaster recovery exercise for Aldridge Pay and the identity and secrets platforms by 31 March 2027. Record actual against target RTO and revise PLN-03 with the observed results. | M32: 10 | N32: — | O32: A.5.30 | P32: Sanjay Mehta | Q32: 31 Mar 2027 | R32: W-07
A33: A.5.30 | B33: ICT readiness for business continuity | C33: Organisational | D33: Yes | E33: Multi-availability-zone architecture with cross-region DR. Backups automated and encrypted. Recovery procedures documented per service. | F33: PLN-03 recovery procedures reviewed. Quarterly component failover test results Q1 and Q2 2026 inspected. | G33: Partially implemented | I33: 2 | J33: ICT readiness is designed but not verified. Restore testing is performed at component level only; a full restore of the Aldridge Credit servicing estate has never been performed. | K33: P2 | L33: Extend the DR exercise programme to cover full restore of A-03, A-04 and A-05. Test at least annually thereafter and report results to the ERC. | M33: 20 | N33: — | O33: A.8.14 | P33: Sanjay Mehta | Q33: 31 Mar 2027 | R33: W-07
A34: A.5.31 | B34: Legal, statutory, regulatory and contractual requirements | C34: Organisational | D34: Yes | E34: Legal maintains an obligations register covering PCI DSS, state money transmitter licences, FCA rules, UK GDPR and state breach laws. Reviewed quarterly. | F34: Obligations register reviewed 2 Sep 2026. Quarterly review evidenced for Q1 and Q2 2026. | G34: Implemented | H34: Design and operation adequate | I34: 3
A35: A.5.32 | B35: Intellectual property rights | C35: Organisational | D35: Yes | E35: Software licensing managed through Jamf and Intune for managed applications. Open source licence scanning in CI. | F35: Jamf and Intune licence reports reviewed. SCA licence scanning configuration inspected. No SAM process located. | G35: Partially implemented | I35: 2 | J35: Licence position for the approximately 40 unregistered SaaS applications is unknown, as is whether any are being used beyond their licensed terms. | K35: P3 | L35: Include licence compliance in the SaaS triage exercise under A.5.23. Establish a software asset management process covering acquisition and true-up. | M35: 5 | N35: — | O35: A.5.23 | P35: Sanjay Mehta | Q35: 30 Jun 2027 | R35: W-04
A36: A.5.33 | B36: Protection of records | C36: Organisational | D36: Yes | E36: SCH-01 Records Retention Schedule published. Legal hold process operated by the General Counsel. Records protected by access control and encryption. | F36: SCH-01 reviewed. Snowflake retention query executed with the data team 4 Sep 2026: borrower records identified predating the stated period. | G36: Partially implemented | H36: Design adequate; operation deficient (schedule not enforced) | I36: 2 | J36: The retention schedule is not technically enforced. Borrower data in Snowflake (A-09) is held beyond the stated retention period, so records are retained without a lawful or business basis. | K36: P2 | L36: Implement automated retention enforcement in Snowflake and the secure data zone. Reconcile actual retention against SCH-01 and remediate the existing overage. Report exceptions quarterly. | M36: 25 | N36: — | O36: A.5.9 | P36: Claire Bennett | Q36: 31 Mar 2027 | R36: W-09
A37: A.5.34 | B37: Privacy and protection of personal identifiable information | C37: Organisational | D37: Yes | E37: DPO appointed. Privacy notices published. DPIAs performed for new processing. Lawful transfer mechanisms documented for cross-border flows. | F37: LEG-POL-01, privacy notices and 4 DPIAs reviewed. Interview: Data Protection Officer. | G37: Partially implemented | I37: 2 | J37: The privacy framework is sound in design but is undermined by the retention overage at A.5.33, which breaches the UK GDPR storage limitation principle for identifiable borrower data. | K37: P2 | L37: Close the retention gap under A.5.33. Add a privacy compliance measure to the quarterly DPO report covering retention conformance and DPIA completeness. | M37: 8 | N37: — | O37: A.5.33 | P37: Sofia Kallio | Q37: 31 Mar 2027 | R37: W-09
A38: A.5.35 | B38: Independent review of information security | C38: Organisational | D38: Yes | E38: Annual PCI DSS assessment by an external QSA. SOC 2 Type II audit annually. Internal Audit reports independently to the Audit Committee. | F38: PCI AOC and SOC 2 report reviewed. Internal Audit 2026 plan inspected: no ISMS engagement. | G38: Partially implemented | I38: 2 | J38: Independent review covers PCI scope and SOC 2 criteria but has never covered the ISMS as a whole. No independent review of information security against ISO/IEC 27001 has been performed. | K38: P2 | L38: Add an ISMS review to the Internal Audit plan for 2027 covering Annex A and clauses 4 to 10. Define a review cycle so that the whole ISMS is covered over three years. | M38: 5 | N38: — | O38: 9.2 | P38: Faisal Rahman | Q38: 31 Mar 2027
A39: A.5.36 | B39: Compliance with policies, rules and standards for information security | C39: Organisational | D39: Yes | E39: Compliance is evidenced for PCI-scoped controls. Access recertification, patching SLAs and training completion are measured. | F39: Five compliance spreadsheets inspected. No version history, no approval records, 3 with conflicting content. | G39: Partially implemented | H39: Design deficient (no compliance monitoring calendar) and tooling inadequate | I39: 2 | J39: There is no systematic compliance monitoring across the whole control set. Policies, exceptions, risks and reviews are tracked across five uncontrolled spreadsheets, so compliance cannot be demonstrated on demand. | K39: P2 | L39: Procure and implement GRC tooling to hold policies, controls, exceptions, risks and evidence in one controlled system. Define a compliance monitoring calendar covering every applicable control. | M39: 20 | N39: 120000 | O39: — | P39: Chidi Eze | Q39: 31 Mar 2027 | R39: W-13
A40: A.5.37 | B40: Documented operating procedures | C40: Organisational | D40: Yes | E40: SOC runbooks and platform engineering procedures are documented and maintained. Procedures for corporate, finance and people processes are patchy. | F40: SOC and platform runbook repositories reviewed. Sample of 8 security-relevant processes outside engineering: 3 documented. | G40: Partially implemented | I40: 2 | J40: Documentation coverage is uneven. Several security-relevant operational activities outside engineering rely on individual knowledge rather than documented procedure. | K40: P3 | L40: Inventory security-relevant operating procedures across all functions. Document the gaps to a common template and place them under version control in the GRC platform. | M40: 18 | N40: — | O40: A.5.36 | P40: Sanjay Mehta | Q40: 30 Jun 2027 | R40: W-13
A41: A.6.1 | B41: Screening | C41: People | D41: Yes | E41: Background screening performed for all workers before start date, through a third-party provider, covering identity, right to work, criminal record and employment history. Enhanced screening for privileged and finance roles. | F41: Screening provider reports sampled, 15 of 15 joiners 2026 screened before start date. | G41: Implemented | H41: Design and operation adequate | I41: 3
A42: A.6.2 | B42: Terms and conditions of employment | C42: People | D42: Yes | E42: Employment contracts and contractor agreements include information security and confidentiality obligations that survive termination. | F42: Employment contract template and contractor agreement reviewed. | G42: Implemented | H42: Design and operation adequate | I42: 3
A43: A.6.3 | B43: Information security awareness, education and training | C43: People | D43: Yes | E43: Annual training through KnowBe4 at 91% completion. Quarterly phishing simulation, most recent click rate 14.2% and report rate 31.0%. Induction training required before access is granted. | F43: KnowBe4 completion report 31 Aug 2026: 91.0%. Q2 2026 campaign report reviewed. No intervention records located for 47 repeat clickers. | G43: Partially implemented | H43: Design deficient (no intervention pathway) and operation deficient (91% completion) | I43: 2 | J43: Completion is short of target, with the residual 9% concentrated in Sales and the London office. Phishing simulation results are not linked to any follow-up: 47 repeat clickers have received no targeted intervention. Training is not differentiated by role. | K43: P2 | L43: Deliver the security awareness programme under AFT-ISMS-PRG-01, including role-based content, automatic enrolment of simulation failures into targeted modules, and escalation to line managers for non-completion. | M43: 30 | N43: 45000 | O43: — | P43: Helen Achebe-Ward | Q43: 31 Mar 2027 | R43: W-14, W-15
A44: A.6.4 | B44: Disciplinary process | C44: People | D44: Yes | E44: HR-POL-02 Disciplinary Procedure applies to security policy breaches. Referenced from POL-01, POL-02 and POL-03. Applied consistently across both entities. | F44: HR-POL-02 reviewed. Interview: VP People Operations. | G44: Implemented | H44: Design and operation adequate | I44: 3
A45: A.6.5 | B45: Responsibilities after termination or change of employment | C45: People | D45: Yes | E45: Confidentiality obligations survive termination by contract. PRO-03 covers revocation, asset return and, for privileged holders, credential rotation within 24 hours. | F45: Contract clauses reviewed. PRO-03 credential rotation step evidenced for 2 privileged leavers in 2026. | G45: Implemented | H45: Design and operation adequate | I45: 3
A46: A.6.6 | B46: Confidentiality or non-disclosure agreements | C46: People | D46: Yes | E46: NDAs executed with all suppliers and counterparties before Confidential information is shared. Employee confidentiality terms in contracts. | F46: NDA templates reviewed. No central register produced on request; contractor NDA status could not be evidenced. | G46: Partially implemented | I46: 2 | J46: No periodic review of NDA coverage. Contractor and temporary worker NDA status is not centrally tracked, so it cannot be demonstrated that every individual with access has current confidentiality terms. | K46: P3 | L46: Build a central register of confidentiality agreements covering workers and third parties. Review annually and at contract renewal. Link NDA status to access provisioning. | M46: 8 | N46: — | O46: — | P46: Jonathan Reyes | Q46: 30 Jun 2027
A47: A.6.7 | B47: Remote working | C47: People | D47: Yes | E47: POL-01 section 3.8 sets remote working requirements. Zero trust access with device posture evaluation. Managed endpoints with encryption and EDR. | F47: POL-01 s3.8 reviewed. Zero trust access policy configuration inspected. | G47: Implemented | H47: Design and operation adequate | I47: 3
A48: A.6.8 | B48: Information security event reporting | C48: People | D48: Yes | E48: POL-02 section 4 places a reporting duty on every worker with a one-hour expectation. Report Phishing button in the mail client with 31.0% report rate. Security hotline and service portal route available. | F48: POL-02 s4 reviewed. Report Phishing telemetry Q2 2026: 189 reports, median 11 minutes. | G48: Implemented | H48: Design and operation adequate | I48: 4
A49: A.7.1 | B49: Physical security perimeters | C49: Physical | D49: Yes | E49: Austin office has a defined and controlled perimeter with reception, badge-controlled doors and a separately secured comms room. London office occupies a floor of a multi-tenant building with landlord-controlled perimeter. | F49: Austin walkthrough 3 Sep 2026. London: lease reviewed; landlord security arrangements not obtained. | G49: Partially implemented | I49: 2 | J49: The London perimeter is outside Aldridge control. The company cannot evidence the adequacy of perimeter controls at a site where 140 workers handle Confidential information. | K49: P3 | L49: Obtain the landlord's security arrangements and assess them. Where inadequate, install Aldridge-controlled access at the floor boundary. Record the residual risk and accept it formally if it cannot be closed. | M49: 5 | N49: — | O49: A.7.2 | P49: Grace Lindberg | Q49: 30 Jun 2027 | R49: W-11
A50: A.7.2 | B50: Physical entry | C50: Physical | D50: Yes | E50: Austin uses individually issued badges with logged entry and visitor escorting. London access credentials are issued and administered by the building landlord. | F50: Austin badge system export reviewed. London: access holder list requested from landlord, not provided within the assessment period. | G50: Partially implemented | I50: 2 | J50: Aldridge cannot produce a list of who holds London office access, cannot revoke access directly on termination, and does not receive entry logs. Leaver revocation for the London site depends on a landlord request with no confirmed service level. | K50: P2 | L50: Negotiate direct administrative access or a guaranteed revocation service level with the landlord, with monthly access list provision. If unavailable, install an Aldridge-controlled access layer at the suite entrance. | M50: 12 | N50: 35000 | O50: — | P50: Grace Lindberg | Q50: 31 Mar 2027 | R50: W-11
A51: A.7.3 | B51: Securing offices, rooms and facilities | C51: Physical | D51: Yes | E51: Comms rooms and secure areas separately controlled with restricted access lists. Meeting rooms handling Restricted material identified and controlled. | F51: Austin comms room access list reviewed (7 holders). | G51: Implemented | H51: Design and operation adequate | I51: 3
A52: A.7.4 | B52: Physical security monitoring | C52: Physical | D52: Yes | E52: CCTV coverage of entry points and the comms room at Austin, retained 30 days. Alarm system monitored out of hours. London monitoring is operated by the landlord. | F52: Austin CCTV configuration inspected, 30-day retention confirmed. London: no Aldridge footage access. | G52: Partially implemented | I52: 2 | J52: No monitoring capability or footage access at the London site. An incident there could not be investigated from physical evidence. | K52: P3 | L52: Agree footage access rights with the landlord under the lease or a side letter. Install Aldridge CCTV covering the suite entrance and comms cupboard. | M52: 6 | N52: 18000 | O52: A.7.2 | P52: Grace Lindberg | Q52: 30 Jun 2027 | R52: W-11
A53: A.7.5 | B53: Protecting against physical and environmental threats | C53: Physical | D53: Yes | E53: Production processing is entirely within AWS, where environmental protection is inherited and evidenced through AWS attestation reports. Office risk assessments cover fire and flood. | F53: AWS attestation report reviewed. Austin office fire and flood risk assessment dated Jan 2026. | G53: Implemented | H53: Design and operation adequate | I53: 3
A54: A.7.6 | B54: Working in secure areas | C54: Physical | D54: Yes | E54: Comms room access requires separate approval and is logged. Photography prohibited. Lone working in secure areas restricted. | F54: Secure area procedure reviewed. Austin comms room entry log sampled. | G54: Implemented | H54: Design and operation adequate | I54: 3
A55: A.7.7 | B55: Clear desk and clear screen | C55: Physical | D55: Yes | E55: POL-04 section 6.4 requires clear desk for Confidential and Restricted material. Automatic screen lock enforced at 15 minutes by device management. | F55: POL-04 s6.4 reviewed. MDM screen lock configuration inspected. No walkthrough or spot check records exist. | G55: Partially implemented | H55: Design adequate; operation unverified (no compliance checking) | I55: 2 | J55: Screen locking is enforced technically but clear desk compliance has never been verified. No walkthrough or spot check has been performed at either site. | K55: P3 | L55: Introduce quarterly clear desk walkthroughs at both offices with recorded findings. Report results to the Security Steering Group and address repeat offenders through line management. | M55: 4 | N55: — | O55: — | P55: Grace Lindberg | Q55: 30 Jun 2027
A56: A.7.8 | B56: Equipment siting and protection | C56: Physical | D56: Yes | E56: Minimal on-premises equipment. Comms room equipment racked, secured and sited away from environmental hazards. | F56: Austin comms room walkthrough 3 Sep 2026. | G56: Implemented | H56: Design and operation adequate | I56: 3
A57: A.7.9 | B57: Security of assets off-premises | C57: Physical | D57: Yes | E57: POL-01 section 3.4 covers device handling off premises. Full disk encryption, EDR and remote wipe on all endpoints. Loss reporting within four hours. | F57: MDM encryption and remote wipe configuration inspected: 610 of 610 endpoints encrypted. | G57: Implemented | H57: Design and operation adequate | I57: 3
A58: A.7.10 | B58: Storage media | C58: Physical | D58: Yes | E58: Removable media restricted by device management and permitted only on documented business need. Company-issued and encrypted. Personal media blocked at the endpoint. | F58: MDM removable media policy inspected. Sample of media issuance records reviewed. | G58: Implemented | H58: Design and operation adequate | I58: 3
A59: A.7.11 | B59: Supporting utilities | C59: Physical | D59: Yes | E59: Production utilities inherited from AWS. Austin comms room supported by UPS with tested failover. London utilities are landlord-provided. | F59: AWS attestation reviewed. Austin UPS test record dated May 2026. | G59: Implemented | H59: Design and operation adequate | I59: 3
A60: A.7.12 | B60: Cabling security | C60: Physical | D60: Yes | E60: Austin cabling is contained within the secured comms room and protected risers. London cabling passes through landlord-managed risers. | F60: Austin riser walkthrough. London: landlord-managed, not inspected. | G60: Partially implemented | I60: 2 | J60: Cabling in the London building is not under Aldridge control or inspection. Low exposure given no Restricted processing occurs on premises, but it cannot be evidenced. | K60: P4 | L60: Document the reliance on the landlord and record it as an accepted risk in the risk register, subject to confirmation that no Restricted data traverses on-premises cabling. | M60: 2 | N60: — | O60: A.7.2 | P60: Grace Lindberg | Q60: Post-certification | R60: W-11
A61: A.7.13 | B61: Equipment maintenance | C61: Physical | D61: Yes | E61: Limited owned equipment. Comms room hardware under vendor maintenance contract with records retained. Endpoint replacement on a three-year cycle. | F61: Maintenance contract and service records reviewed. | G61: Implemented | H61: Design and operation adequate | I61: 3
A62: A.7.14 | B62: Secure disposal or re-use of equipment | C62: Physical | D62: Yes | E62: POL-04 section 7 requires cryptographic erasure or certified destruction. Certificates of destruction retained. Disposal recorded in the asset register. | F62: Destruction certificates sampled, 6 of 6 disposals 2026 evidenced. Asset register disposal entries reconciled. | G62: Implemented | H62: Design and operation adequate | I62: 3
A63: A.8.1 | B63: User endpoint devices | C63: Technological | D63: Yes | E63: All 610 endpoints enrolled in Jamf or Intune with disk encryption, CrowdStrike EDR and automatic patching. Administrative rights granted by exception only. | F63: Jamf and Intune compliance reports 1 Sep 2026: 610 enrolled, 610 encrypted, 598 with current EDR. | G63: Implemented | H63: Design and operation adequate | I63: 4
A64: A.8.2 | B64: Privileged access rights | C64: Technological | D64: Yes | E64: CyberArk just-in-time elevation with four-hour maximum session. No standing production privilege. Break-glass accounts sealed, alerted and reconciled. Privileged sessions recorded and retained 12 months. | F64: CyberArk configuration inspected. Privileged session recording sampled. Break-glass reconciliation records for 3 uses in 2026 reviewed. | G64: Implemented | H64: Design and operation adequate | I64: 4
A65: A.8.3 | B65: Information access restriction | C65: Technological | D65: Yes | E65: Role-based access enforced through Okta groups mapped to application entitlements. Restricted data access requires named grant with CISO approval. | F65: Okta group-to-entitlement mapping inspected for 6 applications. | G65: Implemented | H65: Design and operation adequate | I65: 3
A66: A.8.4 | B66: Access to source code | C66: Technological | D66: Yes | E66: GitHub Enterprise with branch protection, required reviews, CODEOWNERS enforcement and signed commits. Repository access granted by team with quarterly recertification. | F66: GitHub organisation settings inspected: branch protection and CODEOWNERS enforced on 41 of 41 production repositories. | G66: Implemented | H66: Design and operation adequate | I66: 3
A67: A.8.5 | B67: Secure authentication | C67: Technological | D67: Yes | E67: MFA universal, FIDO2 phishing-resistant for privileged access. SMS one-time passcodes not accepted for privileged access. Session timeouts enforced at 15 minutes, 10 for privileged. | F67: Okta authentication policies inspected. Privileged policy confirmed to exclude SMS OTP. | G67: Implemented | H67: Design and operation adequate | I67: 4
A68: A.8.6 | B68: Capacity management | C68: Technological | D68: Yes | E68: Autoscaling configured across production services. Utilisation monitored with alerting. Capacity reviewed reactively when alerts fire. | F68: Autoscaling configuration inspected. No capacity plan produced on request. | G68: Partially implemented | I68: 2 | J68: Capacity management is reactive. There is no forward capacity plan tied to the 28% growth rate, and no documented capacity requirements for the services with one-hour recovery objectives. | K68: P4 | L68: Produce an annual capacity plan covering compute, storage, database and third-party rate limits, refreshed quarterly against actual growth. | M68: 8 | N68: — | O68: — | P68: Sanjay Mehta | Q68: Post-certification
A69: A.8.7 | B69: Protection against malware | C69: Technological | D69: Yes | E69: CrowdStrike Falcon deployed across endpoints and servers with 98% coverage. Detection tuned and monitored by the SOC. Email and web filtering in place. | F69: CrowdStrike console 1 Sep 2026: 98.1% coverage; 12 uncovered hosts identified in the uncodified estate. | G69: Implemented | H69: Design and operation adequate | I69: 3
A70: A.8.8 | B70: Management of technical vulnerabilities | C70: Technological | D70: Yes | E70: Wiz for cloud and container scanning, SCA in CI, annual external penetration test. Remediation SLAs defined by severity and met with evidenced tracking. | F70: Wiz findings and SLA compliance report Aug 2026 reviewed. Penetration test report Jun 2026 reviewed with remediation tracker. | G70: Implemented | H70: Design and operation adequate | I70: 4
A71: A.8.9 | B71: Configuration management | C71: Technological | D71: Yes | E71: Approximately 80% of the estate is defined in Terraform with drift detection. Baseline hardening applied through golden images and Wiz benchmarks. | F71: Terraform state reconciled to AWS inventory 4 Sep 2026: 79.6% codified. Wiz benchmark compliance report reviewed. | G71: Partially implemented | H71: Design adequate for the codified estate; no design covers the remainder | I71: 2 | J71: The remaining 20%, largely older Aldridge Pay components, is not codified. Configuration for those systems is semi-manual, undocumented and not subject to drift detection, and it sits inside the cardholder data environment. | K71: P2 | L71: Codify the remaining Aldridge Pay estate in Terraform, prioritising CDE components. Where migration is not feasible before certification, document the baseline configuration and introduce compensating configuration monitoring. | M71: 60 | N71: — | O71: — | P71: Sanjay Mehta | Q71: 31 Mar 2027 | R71: W-12
A72: A.8.10 | B72: Information deletion | C72: Technological | D72: Yes | E72: Deletion procedures documented in POL-04 section 7. Cryptographic erasure used for cloud storage. Customer deletion requests fulfilled by the DPO within statutory timeframes. | F72: POL-04 s7 reviewed. No automated deletion jobs located in Snowflake or the secure data zone. | G72: Partially implemented | I72: 2 | J72: Routine deletion at end of retention is not automated. Borrower data persists in Snowflake beyond the retention period, so information is not being deleted when no longer required. | K72: P2 | L72: Implement automated deletion jobs aligned to SCH-01 across Snowflake, the secure data zone and backups. Evidence the first full cycle before the Stage 2 audit. | M72: 20 | N72: — | O72: A.5.33 | P72: Claire Bennett | Q72: 31 Mar 2027 | R72: W-09
A73: A.8.11 | B73: Data masking | C73: Technological | D73: Yes | E73: POL-04 section 6.3 prohibits identifiable production data in non-production. A masking and tokenisation pipeline exists and is used by most teams. | F73: Masking pipeline configuration inspected. Exception register reviewed: 4 standing exceptions, 3 without expiry. | G73: Partially implemented | H73: Design adequate; operation deficient (exceptions unmanaged) | I73: 2 | J73: Use of the masking pipeline is not enforced. Exceptions permitting production data in test have been granted and are not consistently time-bound or reviewed, so identifiable borrower data has reached non-production environments. | K73: P2 | L73: Make the masking pipeline the only sanctioned route for production data into non-production and block direct copies at the account boundary. Review and expire all standing exceptions. | M73: 15 | N73: — | O73: A.8.33 | P73: Amara Diallo | Q73: 31 Mar 2027 | R73: W-06
A74: A.8.12 | B74: Data leakage prevention | C74: Technological | D74: Yes | E74: DLP policies active in Google Workspace covering email and drive sharing, tuned for cardholder data patterns. Automatic external forwarding blocked and monitored. | F74: Google Workspace DLP rules inspected. Confirmed no coverage of Snowflake egress or endpoint channels. | G74: Partially implemented | I74: 2 | J74: DLP coverage does not extend to Snowflake query egress, to the approximately 40 unregistered SaaS applications, or to endpoint channels such as removable media and personal cloud sync. | K74: P2 | L74: Extend DLP to Snowflake egress and endpoint channels. Bring sanctioned SaaS applications under CASB inline control once the A.5.23 triage is complete. | M74: 25 | N74: 40000 | O74: A.5.23 | P74: Tomas Vidal | Q74: 31 Mar 2027 | R74: W-04
A75: A.8.13 | B75: Information backup | C75: Technological | D75: Yes | E75: Automated encrypted backups with cross-region replication. Retention aligned to service criticality. Component-level restore tested quarterly with results recorded. | F75: Backup configuration inspected. Restore test records Q1 and Q2 2026 reviewed, component level only. | G75: Implemented | H75: Design and operation adequate | I75: 3
A76: A.8.14 | B76: Redundancy of information processing facilities | C76: Technological | D76: Yes | E76: Multi-availability-zone deployment for all production services. Cross-region disaster recovery configured for us-east-1 to us-west-2. | F76: Architecture documentation reviewed. Cross-region failover last exercised Mar 2025 per the exercise register. | G76: Partially implemented | I76: 2 | J76: Redundancy is architected but the cross-region failover has not been exercised end to end since March 2025, so the stated one-hour recovery objectives for A-01, A-02, A-10, A-11, A-12 and A-15 are unproven. | K76: P2 | L76: Execute a full cross-region failover exercise by 31 March 2027 covering the critical asset set. Record actual recovery times and remediate any that exceed objective. | M76: 20 | N76: — | O76: — | P76: Sanjay Mehta | Q76: 31 Mar 2027 | R76: W-07
A77: A.8.15 | B77: Logging | C77: Technological | D77: Yes | E77: Comprehensive logging across Aldridge Pay, the CDE, Okta, CyberArk, AWS CloudTrail and GitHub, shipped to Splunk with tamper-resistant retention. | F77: Splunk source inventory reconciled to the asset register 4 Sep 2026: 14.8% of Credit servicing components not shipping. | G77: Partially implemented | H77: Design adequate; operation deficient (coverage gap) | I77: 2 | J77: Approximately 15% of the Aldridge Credit servicing estate does not ship logs to Splunk. Activity on those systems, which hold Restricted borrower data, is not centrally recorded and could not be reconstructed after an incident. | K77: P2 | L77: Onboard the remaining Aldridge Credit servicing components to Splunk by 31 January 2027. Introduce a logging coverage measure reconciling the asset register against Splunk sources, reported monthly. | M77: 25 | N77: — | O77: — | P77: Tomas Vidal | Q77: 31 Mar 2027 | R77: W-10
A78: A.8.16 | B78: Monitoring activities | C78: Technological | D78: Yes | E78: Splunk detection content is mature for payments, identity and cloud. 24/7 SOC monitoring with defined triage. | F78: Splunk detection content inventory reviewed (188 use cases). No ATT&CK mapping exists. Credit-specific content: 6 use cases. | G78: Partially implemented | I78: 2 | J78: Detection coverage is thin for the Aldridge Credit estate, compounded by the logging gap at A.8.15. Detection content has not been mapped to a threat framework, so coverage cannot be demonstrated or measured. | K78: P2 | L78: Map existing detection content to MITRE ATT&CK and identify coverage gaps. Build detection content for Aldridge Credit once logging is onboarded. Report coverage quarterly. | M78: 35 | N78: — | O78: A.8.15 | P78: Tomas Vidal | Q78: 31 Mar 2027 | R78: W-10
A79: A.8.17 | B79: Clock synchronisation | C79: Technological | D79: Yes | E79: All systems synchronised to Amazon Time Sync Service. Endpoint clocks managed through device management. Log timestamps consistent in UTC. | F79: NTP configuration inspected across a sample of 12 hosts; all synchronised to Amazon Time Sync. | G79: Implemented | H79: Design and operation adequate | I79: 3
A80: A.8.18 | B80: Use of privileged utility programs | C80: Technological | D80: Yes | E80: Utility use restricted to privileged access workstations and brokered through CyberArk with session recording. Endpoint application control blocks unsanctioned utilities. | F80: Application control policy inspected. CyberArk brokering confirmed for utility access. | G80: Implemented | H80: Design and operation adequate | I80: 3
A81: A.8.19 | B81: Installation of software on operational systems | C81: Technological | D81: Yes | E81: Immutable infrastructure across the Terraform-managed 80%; changes deploy as new images through CI/CD. | F81: Deployment pipeline configuration reviewed. Uncodified estate confirmed to permit manual installation. | G81: Partially implemented | I81: 2 | J81: The 20% of the estate outside Terraform permits manual software installation, without a documented approval or record of what has been installed. | K81: P3 | L81: Extend application control and change recording to the non-codified estate as an interim measure, pending the migration under A.8.9. | M81: 10 | N81: — | O81: A.8.9 | P81: Sanjay Mehta | Q81: 30 Jun 2027 | R81: W-12
A82: A.8.20 | B82: Networks security | C82: Technological | D82: Yes | E82: Security groups, network ACLs and WAF in place. Ingress restricted and egress filtered. Configuration managed as code and monitored by Wiz. | F82: Security group and WAF configuration inspected. Wiz network exposure findings reviewed. | G82: Implemented | H82: Design and operation adequate | I82: 3
A83: A.8.21 | B83: Security of network services | C83: Technological | D83: Yes | E83: Network services provided by AWS under a documented shared responsibility model. Zero trust access service for remote connectivity with device posture checks. | F83: AWS shared responsibility documentation and zero trust access configuration reviewed. | G83: Implemented | H83: Design and operation adequate | I83: 3
A84: A.8.22 | B84: Segregation of networks | C84: Technological | D84: Yes | E84: CDE, secure data zone, production, non-production, corporate and guest networks are mutually isolated in separate AWS accounts and VPCs. Segmentation validated annually by the QSA. | F84: Segmentation test report from the 2026 QSA assessment reviewed. VPC and account boundaries inspected. | G84: Implemented | H84: Design and operation adequate | I84: 4
A85: A.8.23 | B85: Web filtering | C85: Technological | D85: Yes | E85: Secure web gateway filters known malicious and high-risk categories on managed endpoints. | F85: Secure web gateway category configuration inspected. Confirmed no allow-list enforcement for SaaS categories. | G85: Partially implemented | I85: 2 | J85: Filtering blocks malicious destinations but does not prevent access to unsanctioned software as a service, as evidenced by the 40 applications in use without registration. | K85: P3 | L85: Move the web gateway from category blocking to sanctioned-application allow-listing for cloud storage and productivity categories, once the A.5.23 triage has established the sanctioned list. | M85: 10 | N85: — | O85: A.5.23 | P85: Tomas Vidal | Q85: 30 Jun 2027 | R85: W-04
A86: A.8.24 | B86: Use of cryptography | C86: Technological | D86: Yes | E86: POL-07 and STD-09 issued. Encryption at rest with customer-managed keys for Restricted data. TLS 1.2 minimum in transit. Tokenisation for cardholder data. | F86: POL-07 and STD-09 reviewed. KMS and Vault key inventory exported 4 Sep 2026: 23 keys without a recorded owner. | G86: Partially implemented | H86: Design adequate; operation deficient (inventory incomplete) | I86: 2 | J86: The cryptographic key inventory is incomplete and ownership of several legacy Aldridge Pay keys is unclear. Key rotation for those keys cannot be evidenced, and it is not certain they could be rotated safely in an incident. | K86: P2 | L86: Complete the key inventory across all AWS KMS, Vault and application-managed keys. Assign a named owner and rotation schedule to each. Remediate or retire keys of unclear provenance. | M86: 25 | N86: — | O86: A.5.9 | P86: Sanjay Mehta | Q86: 31 Mar 2027 | R86: W-16
A87: A.8.25 | B87: Secure development life cycle | C87: Technological | D87: Yes | E87: Documented SDLC with mandatory peer review, SAST and SCA in CI, and security testing before release. Secure coding training delivered annually to engineers. | F87: POL-06 reviewed. Interview: Head of Platform Engineering. No threat model artefacts located in any repository. | G87: Partially implemented | H87: Design deficient (no threat modelling stage) | I87: 2 | J87: The lifecycle has no threat modelling stage. Security requirements are therefore identified late, in testing, rather than at design, and design-level flaws are not systematically found. | K87: P2 | L87: Introduce threat modelling as a required design activity for new services and for material changes to existing ones. Train engineering leads and record models as design artefacts in the repository. | M87: 25 | N87: 20000 | O87: A.8.27 | P87: Marcus Lindqvist | Q87: 31 Mar 2027 | R87: W-06
A88: A.8.26 | B88: Application security requirements | C88: Technological | D88: Yes | E88: Security requirements are applied through platform defaults, shared libraries and the secure coding standard. | F88: Sample of 12 user stories from 3 teams reviewed: security acceptance criteria present in 2. | G88: Partially implemented | I88: 2 | J88: Security requirements are not captured explicitly in user stories or acceptance criteria, so they are not consistently tested or traceable to the delivered feature. | K88: P3 | L88: Add security acceptance criteria to the definition of done. Provide a requirements checklist by application type and sample compliance at release review. | M88: 10 | N88: — | O88: A.8.25 | P88: Amara Diallo | Q88: 30 Jun 2027 | R88: W-06
A89: A.8.27 | B89: Secure system architecture and engineering principles | C89: Technological | D89: Yes | E89: Architecture review occurs for significant changes. Platform patterns embed secure defaults such as encryption, least privilege and network isolation. | F89: Architecture review records for 4 significant changes reviewed. No principles document exists. | G89: Partially implemented | H89: Design deficient (principles undocumented, therefore untestable) | I89: 2 | J89: Secure engineering principles are embodied in platform patterns but are not documented as principles, so they are applied by convention and are not testable or auditable. | K89: P2 | L89: Document secure architecture and engineering principles, publish them, and make conformance an explicit item at architecture review with recorded outcomes. | M89: 15 | N89: — | O89: — | P89: Marcus Lindqvist | Q89: 31 Mar 2027 | R89: W-06
A90: A.8.28 | B90: Secure coding | C90: Technological | D90: Yes | E90: Secure coding standard published by language. SAST enforced in CI with blocking thresholds. Dependency scanning with automated upgrade pull requests. Annual training for engineers. | F90: Secure coding standard reviewed. SAST configuration inspected: blocking thresholds confirmed on 41 repositories. | G90: Implemented | H90: Design and operation adequate | I90: 3
A91: A.8.29 | B91: Security testing in development and acceptance | C91: Technological | D91: Yes | E91: SAST, DAST and SCA integrated in CI. Annual external penetration test of production with tracked remediation. Pre-release security testing for material changes. | F91: CI pipeline configuration inspected. Penetration test report Jun 2026 and retest evidence reviewed. | G91: Implemented | H91: Design and operation adequate | I91: 3
A92: A.8.30 | B92: Outsourced development | C92: Technological | D92: No | E92: All software development is performed in-house by employed engineers and by contractors working within Aldridge teams, under Aldridge management, using Aldridge repositories, tooling and the standard SDLC. No development is outsourced to a supplier. | F92: Interview: Chief Technology Officer and Head of Platform Engineering. Contractor engagement model reviewed. No outsourced development arrangements identified. | G92: Not applicable | I92: n/a
A93: A.8.31 | B93: Separation of development, test and production environments | C93: Technological | D93: Yes | E93: Development, test, staging and production run in separate AWS accounts with no network path between them. Separate identity boundaries and credentials. | F93: AWS account structure inspected. Confirmed no network path between environment accounts. | G93: Implemented | H93: Design and operation adequate | I93: 4
A94: A.8.32 | B94: Change management | C94: Technological | D94: Yes | E94: Change Advisory Board meets twice weekly. Automated change records from CI/CD for the codified estate. Emergency change procedure documented. | F94: CAB minutes for 6 weeks reviewed. Change records reconciled to deployment events: 12 unmatched changes in the uncodified estate. | G94: Partially implemented | H94: Design adequate; operation deficient (uncodified estate outside process) | I94: 2 | J94: Changes to the 20% of the estate outside Terraform are semi-manual and not consistently recorded, so a complete change history for the Aldridge Pay estate cannot be produced. | K94: P2 | L94: Require a change record for every production change regardless of estate, enforced by a pre-deployment gate. Reconcile change records to deployment events monthly and investigate unmatched changes. | M94: 15 | N94: — | O94: A.8.9 | P94: Sanjay Mehta | Q94: 31 Mar 2027 | R94: W-12
A95: A.8.33 | B95: Test information | C95: Technological | D95: Yes | E95: POL-04 section 6.3 requires synthetic or masked data in non-production. A masking pipeline is available. | F95: POL-04 s6.3 reviewed. Non-production account inspection identified identifiable borrower data in one test environment. | G95: Partially implemented | I95: 2 | J95: Selection and protection of test information is not controlled. Standing exceptions permit production data in test environments that are held to a lower control standard than the source, contrary to POL-04. | K95: P2 | L95: Withdraw standing exceptions and re-approve only with a defined expiry and equivalent controls. Implement automated detection of production data patterns in non-production accounts. | M95: 12 | N95: — | O95: A.8.11 | P95: Amara Diallo | Q95: 31 Mar 2027 | R95: W-06
A96: A.8.34 | B96: Protection of information systems during audit testing | C96: Technological | D96: Yes | E96: Audit and assessment activity, including penetration testing and the QSA assessment, is coordinated informally between Internal Audit, Security and Platform Engineering. | F96: Interview: Head of Internal Audit. No audit testing standard exists. 2026 penetration test scoping correspondence reviewed. | G96: Not implemented | H96: Design absent | I96: 1 | J96: There is no documented control governing audit testing on operational systems. Scope, timing, access and read-only constraints are agreed case by case with no standing requirements, creating a risk of disruption or unintended change during assessment. | K96: P3 | L96: Document an audit testing standard covering agreement of scope and timing, minimisation of access, read-only preference, logging of audit activity and post-activity review. Apply it to the 2027 penetration test and ISMS internal audit. | M96: 6 | N96: — | O96: 9.2 | P96: Faisal Rahman | Q96: 30 Jun 2027

Sheet Clause Gaps
A1: Management System Requirements — clauses 4 to 10
A2: This is what certification is granted against. Annex A supports these requirements; it does not replace them.
A3: Clause | B3: Requirement | C3: Current state | D3: Evidence reviewed | E3: Status | F3: Gap description | G3: Priority | H3: Remediation action | I3: Effort (days) | J3: External cost (USD) | K3: Predecessor | L3: Owner | M3: Target date
A4: 4.1 | B4: Understanding the organisation and its context | C4: Business context is understood by management and reflected in strategy, but not documented for ISMS purposes. | D4: Interview: Head of Security Governance, CISO. No context documentation produced on request. | E4: Not implemented | F4: No documented determination of internal and external issues relevant to the ISMS. | G4: P1 | H4: Document the internal and external issues affecting the ISMS, including regulatory landscape, customer certification demands, growth rate and cloud dependency. Review annually. | I4: 4 | J4: — | K4: — | L4: Chidi Eze | M4: 31 Jan 2027
A5: 4.2 | B5: Understanding the needs and expectations of interested parties | C5: Requirements of customers, regulators and payment brands are tracked by Legal in the obligations register. | D5: Obligations register reviewed. No interested parties register exists. | E5: Partially implemented | F5: Interested parties and their information security requirements are not identified as an ISMS input; the obligations register serves a different purpose and omits parties such as investors and workers. | G5: P1 | H5: Produce an interested parties register mapping each party to its information security requirements and to the controls that satisfy them. | I5: 3 | J5: — | K5: 4.1 | L5: Chidi Eze | M5: 31 Jan 2027
A6: 4.3 | B6: Determining the scope of the information security management system | C6: A draft scope statement exists covering the three platforms, the AWS regions and both offices. | D6: Draft scope statement v0.3 reviewed, undated and unapproved. | E6: Partially implemented | F6: Scope is drafted but not approved, and cannot be finalised while approximately 40 SaaS applications remain unregistered and therefore unassessed for inclusion. | G6: P1 | H6: Complete the SaaS triage under A.5.23, then finalise and approve the scope statement at the ERC with documented boundaries and interfaces. | I6: 5 | J6: — | K6: A.5.23, A.5.9 | L6: Helen Achebe-Ward | M6: 31 Jan 2027
A7: 4.4 | B7: Information security management system | C7: Security controls operate effectively but are not organised or maintained as a management system. | D7: Assessment of the ISMS as a whole across this engagement. | E7: Not implemented | F7: The ISMS does not exist as an established, implemented and continually improved system. Processes and their interactions are not defined. | G7: P1 | H7: Establish the ISMS: define its processes, their sequence and interaction, and the criteria for their operation. This is the umbrella activity that the other clause gaps sit within. | I7: 12 | J7: — | K7: 4.1, 4.2, 4.3 | L7: Helen Achebe-Ward | M7: 31 Jan 2027
A8: 5.1 | B8: Leadership and commitment | C8: The ERC is genuinely engaged and the CEO chairs it. Security investment has been approved. | D8: ERC minutes Mar-Aug 2026 reviewed. Budget approval for the certification programme evidenced Jul 2026. | E8: Partially implemented | F8: Commitment is real but undocumented against ISMS requirements. No evidence that leadership ensures ISMS requirements are integrated into business processes or that resources are determined for the ISMS specifically. | G8: P1 | H8: Document leadership commitment in POL-05. Record ISMS resourcing decisions and integration requirements in ERC minutes. | I8: 3 | J8: — | K8: 5.2 | L8: Priya Raghunathan | M8: 31 Jan 2027
A9: 5.2 | B9: Policy | C9: Tier 2 policies are strong and current. No Tier 1 apex policy exists. | D9: Policy library index reviewed. No Tier 1 policy exists. | E9: Not implemented | F9: There is no information security policy that establishes the ISMS, states objectives, includes a commitment to satisfy applicable requirements and to continual improvement, and is communicated as such. | G9: P1 | H9: Draft and approve AFT-ISMS-POL-05 to satisfy clause 5.2 in full. Communicate to all workers and make available to interested parties. | I9: 8 | J9: — | K9: — | L9: Helen Achebe-Ward | M9: 31 Jan 2027
A10: 5.3 | B10: Organisational roles, responsibilities and authorities | C10: Security roles exist and are staffed. Responsibilities appear across individual policies. | D10: Role descriptions for the security function reviewed. No ISMS reporting responsibility assigned. | E10: Partially implemented | F10: ISMS conformance reporting responsibility is not assigned. No single accountable owner is documented for reporting ISMS performance to top management. | G10: P2 | H10: Assign and document ISMS responsibilities and authorities, including the person responsible for reporting ISMS performance to the ERC. | I10: 3 | J10: — | K10: 5.2 | L10: Helen Achebe-Ward | M10: 31 Mar 2027
A11: 6.1.1 | B11: Actions to address risks and opportunities | C11: Risks are discussed at the ERC and captured in a spreadsheet. | D11: Risk spreadsheet reviewed. No ISMS-level risks and opportunities documented. | E11: Not implemented | F11: No documented determination of the risks and opportunities that need to be addressed to give assurance the ISMS can achieve its intended outcomes. | G11: P1 | H11: Document risks and opportunities to the ISMS itself, distinct from information security risks, and the actions to address them. | I11: 4 | J11: — | K11: 4.4 | L11: Chidi Eze | M11: 31 Jan 2027
A12: 6.1.2 | B12: Information security risk assessment | C12: Risk is tracked in a spreadsheet maintained by the Head of Security Governance. Assessment is performed by judgement without a defined method. | D12: Risk spreadsheet reviewed (41 entries, last updated Jun 2026). No methodology document exists. | E12: Not implemented | F12: No documented risk assessment process defining risk acceptance criteria, criteria for performing assessments, risk identification method, or how consistent, valid and comparable results are ensured. | G12: P1 | H12: Define and document the risk assessment methodology, using the impact, likelihood and rating scales in AFT-CTX-01. Deliverable AFT-ISMS-RSK-01 will apply it. | I12: 12 | J12: 15000 | K12: 4.3 | L12: Chidi Eze | M12: 31 Jan 2027
A13: 6.1.3 | B13: Information security risk treatment | C13: Remediation happens but is not framed as risk treatment. Statement of Applicability exists only as draft v0.3. | D13: SoA draft v0.3 reviewed. No risk treatment plan exists. No risk owner approvals located. | E13: Not implemented | F13: No risk treatment process, no risk treatment plan, and no approved Statement of Applicability. Risk owners have not formally approved treatment plans or accepted residual risk. | G13: P1 | H13: Define the risk treatment process. Complete and approve the Statement of Applicability covering all 93 Annex A controls with inclusion or exclusion justification. Produce a risk treatment plan and obtain risk owner approval. | I13: 20 | J13: — | K13: 6.1.2, 8.2 | L13: Chidi Eze | M13: 31 Jan 2027
A14: 6.2 | B14: Information security objectives and planning to achieve them | C14: Security has departmental goals but no ISMS objectives. | D14: Security team OKRs reviewed. These are departmental goals, not ISMS objectives under clause 6.2. | E14: Not implemented | F14: No documented information security objectives that are measurable, monitored, communicated and updated, with plans stating what will be done, by whom, when and how results are evaluated. | G14: P1 | H14: Set measurable information security objectives aligned to risk appetite, with owners, timescales and evaluation method. Approve at the ERC and report progress quarterly. | I14: 5 | J14: — | K14: 5.2, 6.1.2 | L14: Helen Achebe-Ward | M14: 31 Jan 2027
A15: 6.3 | B15: Planning of changes | C15: Technical change is well controlled through the CAB. ISMS change is not. | D15: Interview: Head of Security Governance. No ISMS change process exists. | E15: Partially implemented | F15: Changes to the ISMS itself are not planned in a determined manner. | G15: P3 | H15: Define how ISMS changes are proposed, assessed and approved, and record them. | I15: 2 | J15: — | K15: 4.4 | L15: Chidi Eze | M15: 30 Jun 2027
A16: 7.1 | B16: Resources | C16: Security function is resourced with 14 staff and an approved budget. Certification programme funded. | D16: Organisation chart and approved budget reviewed. Security function headcount 14. | E16: Implemented
A17: 7.2 | B17: Competence | C17: Security staff hold relevant certifications. Training budget available. Competence is managed through normal performance processes. | D17: Certification records for the security team reviewed. No competence requirements documented for ISMS roles. | E17: Partially implemented | F17: Competence requirements for ISMS roles are not documented, and evidence of competence is not retained as documented information. | G17: P2 | H17: Define competence requirements for each ISMS role, assess current holders against them, and retain evidence. | I17: 6 | J17: — | K17: 5.3 | L17: Grace Lindberg | M17: 31 Mar 2027
A18: 7.3 | B18: Awareness | C18: Annual training at 91% completion. Policies communicated at onboarding. | D18: KnowBe4 completion report reviewed: 91.0%. Awareness of the policy not evidenced for the residual 9%. | E18: Partially implemented | F18: Awareness of the information security policy and of the implications of not conforming is not evidenced for the 9% who have not completed training, concentrated in Sales and London. | G18: P2 | H18: Close the completion gap to above 98% and evidence it. Deliver AFT-ISMS-PRG-01 with escalation for non-completion. | I18: 8 | J18: — | K18: A.6.3 | L18: Helen Achebe-Ward | M18: 31 Mar 2027
A19: 7.4 | B19: Communication | C19: Security communicates through Slack, all-hands and targeted briefings. Effective in practice. | D19: Interview: Director of Corporate Communications. No ISMS communication plan exists. | E19: Partially implemented | F19: Internal and external communications relevant to the ISMS are not determined: what, when, with whom and how is not documented. | G19: P3 | H19: Document an ISMS communication plan covering internal and external audiences, triggers and channels. | I19: 3 | J19: — | K19: 4.2 | L19: Nadia Haddad | M19: 30 Jun 2027
A20: 7.5 | B20: Documented information | C20: Policies are version controlled in Google Drive. Registers are held across five spreadsheets with no version control, no approval record and no retention rule. | D20: Five compliance spreadsheets inspected. Policy library version control confirmed adequate; registers not. | E20: Partially implemented | F20: Control of documented information is inadequate. Creation, update, approval, version control, distribution and retention are not consistently applied outside the policy set. | G20: P2 | H20: Implement GRC tooling as the controlled repository for ISMS documented information, with approval workflow, versioning and access control. | I20: 10 | J20: — | K20: A.5.36 | L20: Chidi Eze | M20: 31 Mar 2027
A21: 8.1 | B21: Operational planning and control | C21: Security operations run to defined runbooks in the SOC and platform teams. Coverage is patchy elsewhere. | D21: SOC and platform runbooks reviewed. Coverage assessed against the ISMS process set: incomplete. | E21: Partially implemented | F21: Processes needed to meet information security requirements are not all planned, implemented and controlled with retained documented information demonstrating they were carried out as planned. | G21: P2 | H21: Identify the ISMS operational processes, document them, and define the evidence each produces. | I21: 12 | J21: — | K21: 4.4 | L21: Chidi Eze | M21: 31 Mar 2027
A22: 8.2 | B22: Information security risk assessment (performance) | C22: No risk assessments have been performed to a defined methodology at planned intervals. | D22: No risk assessment records located at any interval. | E22: Not implemented | F22: Risk assessments are not performed at planned intervals or when significant changes occur, and results are not retained as documented information. | G22: P1 | H22: Perform the first full risk assessment under the new methodology (AFT-ISMS-RSK-01). Set a planned interval of at least annually and on significant change. | I22: 18 | J22: — | K22: 6.1.2 | L22: Chidi Eze | M22: 31 Jan 2027
A23: 8.3 | B23: Information security risk treatment (performance) | C23: Remediation is tracked but not as risk treatment against an approved plan. | D23: No risk treatment plan or implementation records located. | E23: Not implemented | F23: The risk treatment plan does not exist and therefore is not implemented, and results are not retained. | G23: P1 | H23: Produce the risk treatment plan from the risk assessment output, obtain risk owner approval, and track implementation to closure. | I23: 14 | J23: — | K23: 6.1.3 | L23: Chidi Eze | M23: 31 Jan 2027
A24: 9.1 | B24: Monitoring, measurement, analysis and evaluation | C24: Operational security metrics are produced monthly: patching SLA, access recertification, phishing results, incident volumes. | D24: Monthly security metrics pack reviewed (Jun-Aug 2026). Metrics measure activity, not ISMS effectiveness. | E24: Partially implemented | F24: Metrics measure activity, not ISMS effectiveness. What needs to be monitored, the methods, and when results are analysed and evaluated are not determined for the ISMS. | G24: P2 | H24: Define ISMS performance measures tied to the information security objectives, with methods, frequency and responsibility. Report to the ERC quarterly. | I24: 8 | J24: — | K24: 6.2 | L24: Chidi Eze | M24: 31 Mar 2027
A25: 9.2 | B25: Internal audit | C25: Internal Audit is independent, reports to the Audit Committee, and audits security topics within its annual plan. | D25: Internal Audit 2026 plan and charter reviewed. No ISMS audit programme exists. | E25: Partially implemented | F25: No internal audit programme covering the ISMS against ISO/IEC 27001 requirements exists. Audit criteria, scope, frequency and methods for the ISMS have not been defined. | G25: P1 | H25: Establish an ISMS internal audit programme covering all clauses and applicable Annex A controls across a defined cycle. Perform at least one full internal audit before the Stage 2 assessment. | I25: 25 | J25: 45000 | K25: 4.4, 8.2 | L25: Faisal Rahman | M25: 31 Jan 2027
A26: 9.3 | B26: Management review | C26: The ERC receives security reporting monthly and makes decisions on it. | D26: ERC minutes reviewed for clause 9.3 inputs. None of the required agenda items evidenced. | E26: Not implemented | F26: No management review is conducted against the clause 9.3 inputs: audit results, interested party feedback, risk assessment status, objectives performance, nonconformities and improvement opportunities. No management review records exist. | G26: P1 | H26: Establish a formal management review at least annually, with the clause 9.3 agenda, held at the ERC and minuted as documented information. | I26: 5 | J26: — | K26: 9.2, 9.1 | L26: Helen Achebe-Ward | M26: 31 Jan 2027
A27: 10.1 | B27: Continual improvement | C27: Improvement occurs through post-incident review actions and audit findings. | D27: Assessed across the engagement. Improvement occurs but is not demonstrable as ISMS improvement. | E27: Partially implemented | F27: Continual improvement of the suitability, adequacy and effectiveness of the ISMS is not demonstrable because the ISMS is not established. | G27: P2 | H27: Once the ISMS is established, evidence improvement through management review outputs, objective performance trends and closed corrective actions. | I27: 3 | J27: — | K27: 9.3 | L27: Helen Achebe-Ward | M27: 31 Mar 2027
A28: 10.2 | B28: Nonconformity and corrective action | C28: Incident post-incident reviews produce actions tracked to closure. Audit findings are tracked by Internal Audit. | D28: Post-incident review process reviewed. No ISMS nonconformity process exists. | E28: Partially implemented | F28: No ISMS nonconformity process exists. Root cause analysis, evaluation of whether similar nonconformities exist, and retention of records of the nature of nonconformities and subsequent actions are not defined for the ISMS. | G28: P2 | H28: Define a nonconformity and corrective action process covering identification, containment, root cause analysis, corrective action and effectiveness review. Hold records in the GRC platform. | I28: 6 | J28: — | K28: 4.4 | L28: Chidi Eze | M28: 31 Mar 2027

Sheet Remediation Plan
A1: Remediation Plan
A2: Gaps grouped into delivery workstreams. Status column is for the programme to maintain.
A3: Workstream / Ref | B3: Item | C3: Priority | D3: Action | E3: Effort (days) | F3: External cost | G3: Predecessor | H3: Owner | I3: Target date | J3: Status | K3: Notes
A4: WS1 — Establish the management system | B4: Lead: Chidi Eze — The clause 4-10 build. Without this there is nothing to certify.
A5: 4.1 | B5: Understanding the organisation and its context | C5: P1 | D5: Document the internal and external issues affecting the ISMS, including regulatory landscape, customer certification demands, growth rate and cloud dependency. Review annually. | E5: 4 | F5: — | G5: — | H5: Chidi Eze | I5: 31 Jan 2027 | J5: Not started
A6: 4.2 | B6: Understanding the needs and expectations of interested parties | C6: P1 | D6: Produce an interested parties register mapping each party to its information security requirements and to the controls that satisfy them. | E6: 3 | F6: — | G6: 4.1 | H6: Chidi Eze | I6: 31 Jan 2027 | J6: Not started
A7: 4.3 | B7: Determining the scope of the information security management system | C7: P1 | D7: Complete the SaaS triage under A.5.23, then finalise and approve the scope statement at the ERC with documented boundaries and interfaces. | E7: 5 | F7: — | G7: A.5.23, A.5.9 | H7: Chidi Eze | I7: 31 Jan 2027 | J7: Not started
A8: 4.4 | B8: Information security management system | C8: P1 | D8: Establish the ISMS: define its processes, their sequence and interaction, and the criteria for their operation. This is the umbrella activity that the other clause gaps sit within. | E8: 12 | F8: — | G8: 4.1, 4.2, 4.3 | H8: Chidi Eze | I8: 31 Jan 2027 | J8: Not started
A9: 5.1 | B9: Leadership and commitment | C9: P1 | D9: Document leadership commitment in POL-05. Record ISMS resourcing decisions and integration requirements in ERC minutes. | E9: 3 | F9: — | G9: 5.2 | H9: Chidi Eze | I9: 31 Jan 2027 | J9: Not started
A10: 5.2 | B10: Policy | C10: P1 | D10: Draft and approve AFT-ISMS-POL-05 to satisfy clause 5.2 in full. Communicate to all workers and make available to interested parties. | E10: 8 | F10: — | G10: — | H10: Chidi Eze | I10: 31 Jan 2027 | J10: Not started
A11: 5.3 | B11: Organisational roles, responsibilities and authorities | C11: P2 | D11: Assign and document ISMS responsibilities and authorities, including the person responsible for reporting ISMS performance to the ERC. | E11: 3 | F11: — | G11: 5.2 | H11: Chidi Eze | I11: 31 Mar 2027 | J11: Not started
A12: 6.1.1 | B12: Actions to address risks and opportunities | C12: P1 | D12: Document risks and opportunities to the ISMS itself, distinct from information security risks, and the actions to address them. | E12: 4 | F12: — | G12: 4.4 | H12: Chidi Eze | I12: 31 Jan 2027 | J12: Not started
A13: 6.1.2 | B13: Information security risk assessment | C13: P1 | D13: Define and document the risk assessment methodology, using the impact, likelihood and rating scales in AFT-CTX-01. Deliverable AFT-ISMS-RSK-01 will apply it. | E13: 12 | F13: 15000 | G13: 4.3 | H13: Chidi Eze | I13: 31 Jan 2027 | J13: Not started
A14: 6.1.3 | B14: Information security risk treatment | C14: P1 | D14: Define the risk treatment process. Complete and approve the Statement of Applicability covering all 93 Annex A controls with inclusion or exclusion justification. Produce a risk treatment plan and obtain risk owner approval. | E14: 20 | F14: — | G14: 6.1.2, 8.2 | H14: Chidi Eze | I14: 31 Jan 2027 | J14: Not started
A15: 6.2 | B15: Information security objectives and planning to achieve them | C15: P1 | D15: Set measurable information security objectives aligned to risk appetite, with owners, timescales and evaluation method. Approve at the ERC and report progress quarterly. | E15: 5 | F15: — | G15: 5.2, 6.1.2 | H15: Chidi Eze | I15: 31 Jan 2027 | J15: Not started
A16: 6.3 | B16: Planning of changes | C16: P3 | D16: Define how ISMS changes are proposed, assessed and approved, and record them. | E16: 2 | F16: — | G16: 4.4 | H16: Chidi Eze | I16: 30 Jun 2027 | J16: Not started
A17: 7.2 | B17: Competence | C17: P2 | D17: Define competence requirements for each ISMS role, assess current holders against them, and retain evidence. | E17: 6 | F17: — | G17: 5.3 | H17: Chidi Eze | I17: 31 Mar 2027 | J17: Not started
A18: 7.4 | B18: Communication | C18: P3 | D18: Document an ISMS communication plan covering internal and external audiences, triggers and channels. | E18: 3 | F18: — | G18: 4.2 | H18: Chidi Eze | I18: 30 Jun 2027 | J18: Not started
A19: 7.5 | B19: Documented information | C19: P2 | D19: Implement GRC tooling as the controlled repository for ISMS documented information, with approval workflow, versioning and access control. | E19: 10 | F19: — | G19: A.5.36 | H19: Chidi Eze | I19: 31 Mar 2027 | J19: Not started
A20: 8.1 | B20: Operational planning and control | C20: P2 | D20: Identify the ISMS operational processes, document them, and define the evidence each produces. | E20: 12 | F20: — | G20: 4.4 | H20: Chidi Eze | I20: 31 Mar 2027 | J20: Not started
A21: 8.2 | B21: Information security risk assessment (performance) | C21: P1 | D21: Perform the first full risk assessment under the new methodology (AFT-ISMS-RSK-01). Set a planned interval of at least annually and on significant change. | E21: 18 | F21: — | G21: 6.1.2 | H21: Chidi Eze | I21: 31 Jan 2027 | J21: Not started
A22: 8.3 | B22: Information security risk treatment (performance) | C22: P1 | D22: Produce the risk treatment plan from the risk assessment output, obtain risk owner approval, and track implementation to closure. | E22: 14 | F22: — | G22: 6.1.3 | H22: Chidi Eze | I22: 31 Jan 2027 | J22: Not started
A23: 9.1 | B23: Monitoring, measurement, analysis and evaluation | C23: P2 | D23: Define ISMS performance measures tied to the information security objectives, with methods, frequency and responsibility. Report to the ERC quarterly. | E23: 8 | F23: — | G23: 6.2 | H23: Chidi Eze | I23: 31 Mar 2027 | J23: Not started
A24: 9.2 | B24: Internal audit | C24: P1 | D24: Establish an ISMS internal audit programme covering all clauses and applicable Annex A controls across a defined cycle. Perform at least one full internal audit before the Stage 2 assessment. | E24: 25 | F24: 45000 | G24: 4.4, 8.2 | H24: Chidi Eze | I24: 31 Jan 2027 | J24: Not started
A25: 9.3 | B25: Management review | C25: P1 | D25: Establish a formal management review at least annually, with the clause 9.3 agenda, held at the ERC and minuted as documented information. | E25: 5 | F25: — | G25: 9.2, 9.1 | H25: Chidi Eze | I25: 31 Jan 2027 | J25: Not started
A26: 10.1 | B26: Continual improvement | C26: P2 | D26: Once the ISMS is established, evidence improvement through management review outputs, objective performance trends and closed corrective actions. | E26: 3 | F26: — | G26: 9.3 | H26: Chidi Eze | I26: 31 Mar 2027 | J26: Not started
A27: 10.2 | B27: Nonconformity and corrective action | C27: P2 | D27: Define a nonconformity and corrective action process covering identification, containment, root cause analysis, corrective action and effectiveness review. Hold records in the GRC platform. | E27: 6 | F27: — | G27: 4.4 | H27: Chidi Eze | I27: 31 Mar 2027 | J27: Not started
A28: A.5.1 | B28: Policies for information security | C28: P1 | D28: Draft, approve and publish AFT-ISMS-POL-05 Information Security Policy at Tier 1, signed by the CEO. Map every Tier 2 policy and standard to it and to the SoA. Establish an annual policy review calendar. | E28: 8 | F28: — | G28: — | H28: Chidi Eze | I28: 31 Jan 2027 | J28: Not started
A29: A.5.2 | B29: Information security roles and responsibilities | C29: P2 | D29: Produce a single ISMS roles and responsibilities matrix covering all Annex A control owners and clause responsibilities. Ratify at the Executive Risk Committee and reference it from POL-05. | E29: 6 | F29: — | G29: 5.2 | H29: Chidi Eze | I29: 31 Mar 2027 | J29: Not started
A30: A.5.4 | B30: Management responsibilities | C30: P2 | D30: Document management responsibilities in POL-05. Add a standing ISMS agenda item to the ERC with recorded decisions and actions. | E30: 3 | F30: — | G30: 5.2 | H30: Chidi Eze | I30: 31 Mar 2027 | J30: Not started
A32: WS2 — Asset and cloud scope integrity | B32: Lead: Claire Bennett — The SaaS estate must be known before scope can be approved or risk assessed.
A33: A.5.9 | B33: Inventory of information and other associated assets | C33: P1 | D33: Reconcile the CASB discovery output against the asset register. Assign an owner and classification to every application, or decommission it. Establish monthly CASB-to-register reconciliation as a standing control. | E33: 30 | F33: — | G33: — | H33: Claire Bennett | I33: 31 Jan 2027 | J33: Not started
A34: A.5.23 | B34: Information security for use of cloud services | C34: P1 | D34: Triage the 40 discovered applications by data classification. Block or sanction each one. Route SaaS procurement through Okta and Procurement so that acquisition without assessment is not technically possible. | E34: 25 | F34: 30000 | G34: A.5.9 | H34: Claire Bennett | I34: 31 Jan 2027 | J34: Not started
A35: A.5.32 | B35: Intellectual property rights | C35: P3 | D35: Include licence compliance in the SaaS triage exercise under A.5.23. Establish a software asset management process covering acquisition and true-up. | E35: 5 | F35: — | G35: A.5.23 | H35: Claire Bennett | I35: 30 Jun 2027 | J35: Not started
A36: A.8.12 | B36: Data leakage prevention | C36: P2 | D36: Extend DLP to Snowflake egress and endpoint channels. Bring sanctioned SaaS applications under CASB inline control once the A.5.23 triage is complete. | E36: 25 | F36: 40000 | G36: A.5.23 | H36: Claire Bennett | I36: 31 Mar 2027 | J36: Not started
A37: A.8.23 | B37: Web filtering | C37: P3 | D37: Move the web gateway from category blocking to sanctioned-application allow-listing for cloud storage and productivity categories, once the A.5.23 triage has established the sanctioned list. | E37: 10 | F37: — | G37: A.5.23 | H37: Claire Bennett | I37: 30 Jun 2027 | J37: Not started
A39: WS3 — Third-party risk | B39: Lead: Elena Petrova — Clear the reassessment backlog and extend to the onward supply chain.
A40: A.5.19 | B40: Information security in supplier relationships | C40: P2 | D40: Extend POL-09 to cover the full supplier lifecycle including offboarding, data return and destruction. Define security requirements for supplier exit and test them on the next termination. | E40: 8 | F40: — | G40: — | H40: Elena Petrova | I40: 31 Mar 2027 | J40: Not started
A41: A.5.20 | B41: Addressing information security within supplier agreements | C41: P2 | D41: Identify all Tier 1 and Tier 2 agreements lacking the current security schedule. Prioritise renegotiation at next renewal, and seek immediate amendment for Tier 1 suppliers on the critical path. | E41: 15 | F41: 25000 | G41: A.5.19 | H41: Elena Petrova | I41: 31 Mar 2027 | J41: Not started
A42: A.5.21 | B42: Managing information security in the ICT supply chain | C42: P2 | D42: Add mandatory subcontractor disclosure to the TPRM questionnaire and to contract terms, with a notification obligation before any change. Map the fourth parties of all Tier 1 suppliers. | E42: 15 | F42: — | G42: A.5.19 | H42: Elena Petrova | I42: 31 Mar 2027 | J42: Not started
A43: A.5.22 | B43: Monitoring, review and change management of supplier services | C43: P2 | D43: Clear the reassessment backlog, Tier 1 first, by 31 January 2027. Implement continuous supplier monitoring for Tier 1. Add reassessment due dates to the procurement system with automated escalation to the CISO at 30 days overdue. | E43: 35 | F43: — | G43: A.5.19 | H43: Elena Petrova | I43: 31 Mar 2027 | J43: Not started
A45: WS4 — Data lifecycle and retention | B45: Lead: Claire Bennett — Enforce retention technically; close the storage limitation exposure.
A46: A.5.13 | B46: Labelling of information | C46: P3 | D46: Enable default labelling and mandatory label prompts in Google Workspace. Run a labelling remediation campaign on existing shared drives. Report adoption monthly until above 95%. | E46: 12 | F46: — | G46: A.5.9 | H46: Claire Bennett | I46: 30 Jun 2027 | J46: Not started
A47: A.5.33 | B47: Protection of records | C47: P2 | D47: Implement automated retention enforcement in Snowflake and the secure data zone. Reconcile actual retention against SCH-01 and remediate the existing overage. Report exceptions quarterly. | E47: 25 | F47: — | G47: A.5.9 | H47: Claire Bennett | I47: 31 Mar 2027 | J47: Not started
A48: A.5.34 | B48: Privacy and protection of personal identifiable information | C48: P2 | D48: Close the retention gap under A.5.33. Add a privacy compliance measure to the quarterly DPO report covering retention conformance and DPIA completeness. | E48: 8 | F48: — | G48: A.5.33 | H48: Claire Bennett | I48: 31 Mar 2027 | J48: Not started
A49: A.8.10 | B49: Information deletion | C49: P2 | D49: Implement automated deletion jobs aligned to SCH-01 across Snowflake, the secure data zone and backups. Evidence the first full cycle before the Stage 2 audit. | E49: 20 | F49: — | G49: A.5.33 | H49: Claire Bennett | I49: 31 Mar 2027 | J49: Not started
A50: A.8.11 | B50: Data masking | C50: P2 | D50: Make the masking pipeline the only sanctioned route for production data into non-production and block direct copies at the account boundary. Review and expire all standing exceptions. | E50: 15 | F50: — | G50: A.8.33 | H50: Claire Bennett | I50: 31 Mar 2027 | J50: Not started
A51: A.8.33 | B51: Test information | C51: P2 | D51: Withdraw standing exceptions and re-approve only with a defined expiry and equivalent controls. Implement automated detection of production data patterns in non-production accounts. | E51: 12 | F51: — | G51: A.8.11 | H51: Claire Bennett | I51: 31 Mar 2027 | J51: Not started
A53: WS5 — Detection and logging coverage | B53: Lead: Tomas Vidal — Complete logging across Aldridge Credit and formalise threat intelligence.
A54: A.5.6 | B54: Contact with special interest groups | C54: P3 | D54: Take out organisational FS-ISAC membership. Define named representatives and deputies, and a route for intelligence received to reach the SOC and the Security Steering Group. | E54: 2 | F54: 8000 | G54: — | H54: Tomas Vidal | I54: 30 Jun 2027 | J54: Not started
A55: A.5.7 | B55: Threat intelligence | C55: P2 | D55: Define priority intelligence requirements based on the payments and lending threat landscape. Formalise collection sources, analysis cadence and dissemination to the SOC, engineering and the Security Steering Group. Feed intelligence into the risk assessment cycle. | E55: 20 | F55: 60000 | G55: — | H55: Tomas Vidal | I55: 31 Mar 2027 | J55: Not started
A56: A.8.15 | B56: Logging | C56: P2 | D56: Onboard the remaining Aldridge Credit servicing components to Splunk by 31 January 2027. Introduce a logging coverage measure reconciling the asset register against Splunk sources, reported monthly. | E56: 25 | F56: — | G56: — | H56: Tomas Vidal | I56: 31 Mar 2027 | J56: Not started
A57: A.8.16 | B57: Monitoring activities | C57: P2 | D57: Map existing detection content to MITRE ATT&CK and identify coverage gaps. Build detection content for Aldridge Credit once logging is onboarded. Report coverage quarterly. | E57: 35 | F57: — | G57: A.8.15 | H57: Tomas Vidal | I57: 31 Mar 2027 | J57: Not started
A59: WS6 — Platform hardening and change | B59: Lead: Sanjay Mehta — Codify the residual Aldridge Pay estate; complete the key inventory.
A60: A.8.9 | B60: Configuration management | C60: P2 | D60: Codify the remaining Aldridge Pay estate in Terraform, prioritising CDE components. Where migration is not feasible before certification, document the baseline configuration and introduce compensating configuration monitoring. | E60: 60 | F60: — | G60: — | H60: Sanjay Mehta | I60: 31 Mar 2027 | J60: Not started
A61: A.8.19 | B61: Installation of software on operational systems | C61: P3 | D61: Extend application control and change recording to the non-codified estate as an interim measure, pending the migration under A.8.9. | E61: 10 | F61: — | G61: A.8.9 | H61: Sanjay Mehta | I61: 30 Jun 2027 | J61: Not started
A62: A.8.24 | B62: Use of cryptography | C62: P2 | D62: Complete the key inventory across all AWS KMS, Vault and application-managed keys. Assign a named owner and rotation schedule to each. Remediate or retire keys of unclear provenance. | E62: 25 | F62: — | G62: A.5.9 | H62: Sanjay Mehta | I62: 31 Mar 2027 | J62: Not started
A63: A.8.32 | B63: Change management | C63: P2 | D63: Require a change record for every production change regardless of estate, enforced by a pre-deployment gate. Reconcile change records to deployment events monthly and investigate unmatched changes. | E63: 15 | F63: — | G63: A.8.9 | H63: Sanjay Mehta | I63: 31 Mar 2027 | J63: Not started
A64: A.8.6 | B64: Capacity management | C64: P4 | D64: Produce an annual capacity plan covering compute, storage, database and third-party rate limits, refreshed quarterly against actual growth. | E64: 8 | F64: — | G64: — | H64: Sanjay Mehta | I64: Post-certification | J64: Not started
A65: A.5.37 | B65: Documented operating procedures | C65: P3 | D65: Inventory security-relevant operating procedures across all functions. Document the gaps to a common template and place them under version control in the GRC platform. | E65: 18 | F65: — | G65: A.5.36 | H65: Sanjay Mehta | I65: 30 Jun 2027 | J65: Not started
A67: WS7 — Secure engineering | B67: Lead: Marcus Lindqvist — Introduce threat modelling and document engineering principles.
A68: A.5.8 | B68: Information security in project management | C68: P2 | D68: Introduce a mandatory security assessment step at project initiation, sized by risk. Add security sign-off to the delivery lifecycle checklist and record it in Jira. | E68: 10 | F68: — | G68: 5.2 | H68: Marcus Lindqvist | I68: 31 Mar 2027 | J68: Not started
A69: A.8.25 | B69: Secure development life cycle | C69: P2 | D69: Introduce threat modelling as a required design activity for new services and for material changes to existing ones. Train engineering leads and record models as design artefacts in the repository. | E69: 25 | F69: 20000 | G69: A.8.27 | H69: Marcus Lindqvist | I69: 31 Mar 2027 | J69: Not started
A70: A.8.26 | B70: Application security requirements | C70: P3 | D70: Add security acceptance criteria to the definition of done. Provide a requirements checklist by application type and sample compliance at release review. | E70: 10 | F70: — | G70: A.8.25 | H70: Marcus Lindqvist | I70: 30 Jun 2027 | J70: Not started
A71: A.8.27 | B71: Secure system architecture and engineering principles | C71: P2 | D71: Document secure architecture and engineering principles, publish them, and make conformance an explicit item at architecture review with recorded outcomes. | E71: 15 | F71: — | G71: — | H71: Marcus Lindqvist | I71: 31 Mar 2027 | J71: Not started
A73: WS8 — Resilience assurance | B73: Lead: Sanjay Mehta — Prove the recovery objectives that are currently only designed.
A74: A.5.29 | B74: Information security during disruption | C74: P2 | D74: Run a full end-to-end disaster recovery exercise for Aldridge Pay and the identity and secrets platforms by 31 March 2027. Record actual against target RTO and revise PLN-03 with the observed results. | E74: 10 | F74: — | G74: A.5.30 | H74: Sanjay Mehta | I74: 31 Mar 2027 | J74: Not started
A75: A.5.30 | B75: ICT readiness for business continuity | C75: P2 | D75: Extend the DR exercise programme to cover full restore of A-03, A-04 and A-05. Test at least annually thereafter and report results to the ERC. | E75: 20 | F75: — | G75: A.8.14 | H75: Sanjay Mehta | I75: 31 Mar 2027 | J75: Not started
A76: A.8.14 | B76: Redundancy of information processing facilities | C76: P2 | D76: Execute a full cross-region failover exercise by 31 March 2027 covering the critical asset set. Record actual recovery times and remediate any that exceed objective. | E76: 20 | F76: — | G76: — | H76: Sanjay Mehta | I76: 31 Mar 2027 | J76: Not started
A78: WS9 — People and awareness | B78: Lead: Helen Achebe-Ward — Close training completion and link simulation results to intervention.
A79: A.6.3 | B79: Information security awareness, education and training | C79: P2 | D79: Deliver the security awareness programme under AFT-ISMS-PRG-01, including role-based content, automatic enrolment of simulation failures into targeted modules, and escalation to line managers for non-completion. | E79: 30 | F79: 45000 | G79: — | H79: Helen Achebe-Ward | I79: 31 Mar 2027 | J79: Not started
A80: 7.3 | B80: Awareness | C80: P2 | D80: Close the completion gap to above 98% and evidence it. Deliver AFT-ISMS-PRG-01 with escalation for non-completion. | E80: 8 | F80: — | G80: A.6.3 | H80: Helen Achebe-Ward | I80: 31 Mar 2027 | J80: Not started
A81: A.6.6 | B81: Confidentiality or non-disclosure agreements | C81: P3 | D81: Build a central register of confidentiality agreements covering workers and third parties. Review annually and at contract renewal. Link NDA status to access provisioning. | E81: 8 | F81: — | G81: — | H81: Helen Achebe-Ward | I81: 30 Jun 2027 | J81: Not started
A82: A.5.3 | B82: Segregation of duties | C82: P2 | D82: Build a segregation of duties conflict matrix for finance, payments, lending and platform roles. Encode the rules in Okta and the access request workflow so conflicts are blocked, not judged. | E82: 12 | F82: — | G82: A.5.9 | H82: Helen Achebe-Ward | I82: 31 Mar 2027 | J82: Not started
A84: WS10 — Physical security, London | B84: Lead: Grace Lindberg — Resolve or formally accept the landlord dependency.
A85: A.7.1 | B85: Physical security perimeters | C85: P3 | D85: Obtain the landlord's security arrangements and assess them. Where inadequate, install Aldridge-controlled access at the floor boundary. Record the residual risk and accept it formally if it cannot be closed. | E85: 5 | F85: — | G85: A.7.2 | H85: Grace Lindberg | I85: 30 Jun 2027 | J85: Not started
A86: A.7.2 | B86: Physical entry | C86: P2 | D86: Negotiate direct administrative access or a guaranteed revocation service level with the landlord, with monthly access list provision. If unavailable, install an Aldridge-controlled access layer at the suite entrance. | E86: 12 | F86: 35000 | G86: — | H86: Grace Lindberg | I86: 31 Mar 2027 | J86: Not started
A87: A.7.4 | B87: Physical security monitoring | C87: P3 | D87: Agree footage access rights with the landlord under the lease or a side letter. Install Aldridge CCTV covering the suite entrance and comms cupboard. | E87: 6 | F87: 18000 | G87: A.7.2 | H87: Grace Lindberg | I87: 30 Jun 2027 | J87: Not started
A88: A.7.7 | B88: Clear desk and clear screen | C88: P3 | D88: Introduce quarterly clear desk walkthroughs at both offices with recorded findings. Report results to the Security Steering Group and address repeat offenders through line management. | E88: 4 | F88: — | G88: — | H88: Grace Lindberg | I88: 30 Jun 2027 | J88: Not started
A89: A.7.12 | B89: Cabling security | C89: P4 | D89: Document the reliance on the landlord and record it as an accepted risk in the risk register, subject to confirmation that no Restricted data traverses on-premises cabling. | E89: 2 | F89: — | G89: A.7.2 | H89: Grace Lindberg | I89: Post-certification | J89: Not started
A91: WS11 — Assurance and audit | B91: Lead: Faisal Rahman — Independent review of the ISMS and control of audit activity.
A92: A.5.35 | B92: Independent review of information security | C92: P2 | D92: Add an ISMS review to the Internal Audit plan for 2027 covering Annex A and clauses 4 to 10. Define a review cycle so that the whole ISMS is covered over three years. | E92: 5 | F92: — | G92: 9.2 | H92: Faisal Rahman | I92: 31 Mar 2027 | J92: Not started
A93: A.5.36 | B93: Compliance with policies, rules and standards for information security | C93: P2 | D93: Procure and implement GRC tooling to hold policies, controls, exceptions, risks and evidence in one controlled system. Define a compliance monitoring calendar covering every applicable control. | E93: 20 | F93: 120000 | G93: — | H93: Faisal Rahman | I93: 31 Mar 2027 | J93: Not started
A94: A.8.34 | B94: Protection of information systems during audit testing | C94: P3 | D94: Document an audit testing standard covering agreement of scope and timing, minimisation of access, read-only preference, logging of audit activity and post-activity review. Apply it to the 2027 penetration test and ISMS internal audit. | E94: 6 | F94: — | G94: 9.2 | H94: Faisal Rahman | I94: 30 Jun 2027 | J94: Not started
A97: CAPACITY CHECK
A98: Lead | B98: Person-days assigned | C98: Working days available to 31 Mar 2027 | D98: Load | E98: Assessment
A99: Chidi Eze | B99: 208 | C99: 125 | D99: 1.664 | E99: Not deliverable at current resourcing
A100: Claire Bennett | B100: 187 | C100: 125 | D100: 1.496 | E100: Not deliverable at current resourcing
A101: Sanjay Mehta | B101: 186 | C101: 125 | D101: 1.488 | E101: Not deliverable at current resourcing
A102: Tomas Vidal | B102: 82 | C102: 125 | D102: 0.656 | E102: Deliverable only with no other duties
A103: Elena Petrova | B103: 73 | C103: 125 | D103: 0.584 | E103: Deliverable alongside existing duties
A104: Marcus Lindqvist | B104: 60 | C104: 125 | D104: 0.48 | E104: Deliverable alongside existing duties
A105: Helen Achebe-Ward | B105: 58 | C105: 125 | D105: 0.464 | E105: Deliverable alongside existing duties
A106: Faisal Rahman | B106: 31 | C106: 125 | D106: 0.248 | E106: Deliverable alongside existing duties
A107: Grace Lindberg | B107: 29 | C107: 125 | D107: 0.232 | E107: Deliverable alongside existing duties
A109: PROGRAMME TOTAL: 914 internal person-days and approximately $461,000 of external spend, excluding the certification body fee. At a blended internal rate of $900/day the internal effort is approximately $822,600, giving an indicative programme cost of about $1,283,600. The capacity table above is the material finding: the effort assigned to the two heaviest leads exceeds the working days available to them before the Phase 2 deadline, and both hold substantial business-as-usual responsibilities. The plan is not deliverable as assigned. Either a dedicated ISMS manager is appointed and workstreams are reassigned, or the timetable moves. Approving this plan without resolving that is how certification programmes slip six months without anyone deciding that they should.
