Workbook

Sheet Cover & Method
A1: Information Security Risk Assessment
A2: Aldridge Financial Technologies | AFT-ISMS-RSK-01 | Version 2.0 | 9 September 2026 | Classification: Confidential
A5: CHANGES IN VERSION 2.0
B6: Register expanded from 30 to 55 risks following expert review. Twenty-five risks added covering financial crime (sanctions, AML, SAR filing, CIP), single-cloud concentration, supplier financial viability and fourth-party concentration, fraud and settlement loss, data subject rights, and specific regulatory exposures including the NYDFS Part 500 CISO certification.
B7: Every risk now names a threat source from the AFT-CTX-01 section 14 threat profile, and every likelihood estimate now carries a stated evidence base. A Risk Treatment Plan with risk owner sign-off has been added to satisfy clause 6.1.3(e) and (f), which version 1.0 did not.
A9: FRAMEWORK POSITION — READ THIS FIRST
B10: Conducted under NIST SP 800-30 Rev. 1 using FIPS 199 for security categorisation. It operates within the Prepare, Categorize and Select steps of the NIST Risk Management Framework (SP 800-37 Rev. 2). It is NOT a full RMF implementation.
B11: RMF is a seven-step federal system authorisation lifecycle concluding with an Authorizing Official granting an Authorization to Operate. Aldridge has no Authorizing Official, no ATO and no federal system. The Implement, Assess, Authorize and Monitor steps as defined in SP 800-37 do not apply and have not been performed. Describing this as 'an RMF risk assessment' without that qualification would not be defensible.
A13: A NOTE ON INHERENT RISK
B14: This assessment scores inherent risk (the exposure assuming the control environment is absent) alongside residual risk. The approach is contested: some practitioners hold that inherent risk is not meaningfully estimable, since one cannot coherently imagine this organisation operating with no access control at all. It is used here for two reasons: it makes control contribution visible, which supports investment decisions; and it exposes controls that reduce nothing, as at R-05 and R-41 where inherent and residual are equal because the control is ineffective. Where the inherent estimate is weak, the residual figure governs.
A16: SCOPE AND BASIS
A17: Scope | B17: The 22 information assets catalogued in AFT-CTX-01 section 4, and the regulatory obligations at section 1.2.
A18: Method | B18: Asset-based assessment. Threat sources per AFT-CTX-01 section 14. Vulnerabilities drawn from AFT-ISMS-GAP-01 and from inspection.
A19: Inputs | B19: AFT-CTX-01 v2.0; AFT-ISMS-GAP-01 v2.0; AFT-TPRM-ASM-01 v2.0; incident history 2024-2026; obligations register.
A20: Interval | B20: At least annually and on significant change, once clause 8.2 is established.
A22: SCALES
A23: Impact 1-5 | B23: 1 Negligible (<USD 50k) · 2 Minor (50k-500k) · 3 Moderate (500k-2m, reportable breach) · 4 Major (2m-10m, formal regulatory finding) · 5 Severe (>10m, licence or authorisation at risk)
A24: Likelihood 1-5 | B24: 1 Rare (<1 in 10 years) · 2 Unlikely (1 in 3-10 years) · 3 Possible (1 in 1-3 years) · 4 Likely (once in 12 months) · 5 Almost certain (more than once in 12 months, or already occurring)
A25: Rating | B25: Critical 16-25 (Board Audit Committee) · High 10-15 (ERC) · Moderate 5-9 (CISO) · Low 1-4 (asset owner)
A26: Control effectiveness | B26: Strong (reduces likelihood two bands or more) · Effective (one band) · Limited (less than one band) · Ineffective (no reduction; inherent equals residual)
A28: LIMITATIONS
B29: Likelihood estimates are judgement-based and informed by the evidence stated in the Likelihood basis column; they are not actuarial. Impact values use the financial and regulatory anchors in AFT-CTX-01 and have not been separately modelled. No control testing was performed; effectiveness ratings are carried from AFT-ISMS-GAP-01. Risks arising from the approximately 40 unregistered applications are represented in aggregate at R-04, R-45 and R-47 and cannot be individually assessed until that inventory closes. R-40 carries an unsupported likelihood by design: no supplier financial assessment has ever been performed, and recording a placeholder is more honest than implying an estimate exists.

Sheet System Categorisation
A1: FIPS 199 Security Categorisation
A2: Impact level per security objective. Overall category is the high-water mark, per FIPS 199 s3.
A3: ID | B3: Asset | C3: Owner | D3: Information types | E3: Confidentiality | F3: Integrity | G3: Availability | H3: Overall | I3: Rationale
A4: A-01 | B4: Aldridge Pay transaction processing service | C4: Oliver Trent | D4: Cardholder data; payment transaction records; merchant identifiers | E4: High | F4: High | G4: High | H4: High | I4: Authorisation path for USD 14.2bn annualised volume. Loss of integrity permits fraudulent settlement; loss of availability halts merchant revenue across 2,400 platform customers.
A5: A-02 | B5: Cardholder data vault (tokenisation) | C5: Oliver Trent | D5: Cardholder data; tokenisation key material | E5: High | F5: High | G5: High | H5: High | I5: Compromise would expose account data at scale and trigger payment brand and state notification. Detokenisation failure halts all card processing.
A6: A-03 | B6: Aldridge Credit origination platform | C6: Amara Diallo | D6: Borrower personal data; credit decision data; bank account details | E6: High | F6: High | G6: Moderate | H6: High | I6: Holds identifiers and credit files. Integrity loss produces erroneous or unfair lending decisions with fair-lending exposure.
A7: A-04 | B7: Aldridge Credit servicing and collections | C7: Amara Diallo | D7: Borrower personal data; repayment and arrears records; bank details | E7: High | F7: High | G7: Moderate | H7: High | I7: Integrity loss misstates borrower obligations and creates consumer harm and regulatory exposure.
A8: A-05 | B8: Borrower credit file store (secure data zone) | C8: Amara Diallo | D8: Credit files; government identifiers; income and affordability data | E8: High | F8: High | G8: Moderate | H8: High | I8: The most sensitive concentration of personal data in the estate.
A9: A-06 | B9: Aldridge Ledger reconciliation API | C9: Marcus Lindqvist | D9: Transaction and settlement records; merchant balances | E9: Moderate | F9: High | G9: Moderate | H9: High | I9: Integrity is paramount: reconciliation errors propagate into customer settlement and financial reporting.
A10: A-07 | B10: Customer portal and merchant dashboard | C10: Amara Diallo | D10: Merchant account data; transaction summaries; user credentials | E10: Moderate | F10: Moderate | G10: Moderate | H10: Moderate | I10: Principal customer interface. Presents data held authoritatively elsewhere.
A11: A-08 | B11: Public marketing website | C11: Nadia Haddad | D11: Public marketing content; enquiry form submissions | E11: Low | F11: Moderate | G11: Low | H11: Moderate | I11: No sensitive data. Integrity matters: defacement or injected content would damage trust and could be used to phish customers.
A12: A-09 | B12: Snowflake analytics warehouse | C12: Claire Bennett | D12: Aggregated borrower and transaction data; identifiable data beyond retention | E12: High | F12: Moderate | G12: Low | H12: High | I12: Confidentiality is High because identifiable borrower data persists here contrary to SCH-01 (W-09).
A13: A-10 | B13: Fraud decisioning integration | C13: Oliver Trent | D13: Transaction metadata; truncated cardholder data; risk scores | E13: High | F13: High | G13: High | H13: High | I13: Synchronous in the authorisation path and dependent on an external Tier 1 supplier (V-01).
A14: A-11 | B14: Okta identity provider | C14: Ruth Nakamura | D14: Authentication credentials; identity and entitlement data | E14: High | F14: High | G14: High | H14: High | I14: Compromise confers access to every federated system. Unavailability locks out the entire workforce.
... A25: A-22 | B25: London office (landlord-managed access) | C25: Grace Lindberg | D25: Physical documents; workstations | E25: Low | F25: Low | G25: Low | H25: Low | I25: No production processing. Access administration outside Aldridge control (W-11).

Sheet Risk Register
A1: Information Security Risk Register
A2: 55 risks. Scores, ratings, appetite test and approval level are formulas. Threat sources per AFT-CTX-01 s14.
A3: Risk ID | B3: Risk | C3: Assets | D3: TA | E3: Threat source | F3: Appetite category | G3: Threat event | H3: Vulnerability / condition | I3: Existing controls | J3: Inh. I | K3: Inh. L | L3: Inh. score | M3: Inh. rating | N3: Likelihood basis | O3: Control effectiveness | P3: Res. I | Q3: Res. L | R3: Res. score | S3: Res. rating | T3: Max tolerable | U3: Appetite test | V3: Treatment | W3: Risk owner | X3: Target date | Y3: Approval to accept
A4: R-01 | B4: Ransomware encrypts production estate and backups | C4: A-01, A-02, A-03, A-04, A-15 | D4: TA-01 | E4: Organised criminal group | F4: Service availability | G4: Deployment of ransomware following initial access, with attempted destruction of backups before encryption | H4: Cross-region failover has not been exercised end to end since March 2025, so the one-hour recovery objectives are unproven (W-07). | I4: CrowdStrike EDR across endpoints and servers; network segregation into separate accounts; immutable cross-region backups; universal MFA; just-in-time privileged access with no standing production privilege; 24/7 SOC. | J4: 5 | K4: 4 | L4: =J4*K4 -> 20 | M4: =IF(L4>=16,"Critical",IF(L4>=10,"High",IF(L4>=5,"Moderate","Low"))) -> Critical | N4: Sector incident data: ransomware remains the most frequently reported cause of material disruption in financial services. No Aldridge incident to date. Inherent L4 reflects sector frequency; residual L2 reflects tested EDR and segregation. | O4: Effective | P4: 5 | Q4: 2 | R4: =P4*Q4 -> 10 | S4: =IF(R4>=16,"Critical",IF(R4>=10,"High",IF(R4>=5,"Moderate","Low"))) -> High | T4: 9 | U4: =IF(R4<=T4,"Within","EXCEEDS") -> EXCEEDS | V4: Treat | W4: Sanjay Mehta | X4: 31 Mar 2027 | Y4: =IF(S4="Critical","Board Audit Committee",IF(S4="High","Executive Risk Committee",IF(S4="Moderate","CISO","Asset owner"))) -> Executive Risk Committee
A5: R-02 | B5: Compromise of cloud control-plane credentials | C5: A-15, A-11, A-12 | D5: TA-08 | E5: Sophisticated external attacker | F5: Data confidentiality | G5: Theft or misuse of organisation-level AWS credentials granting estate-wide access | H5: Concentration of authority in the management accounts; break-glass credentials exist by necessity. | I5: Root and organisation-owner credentials under dual custody with hardware tokens; CyberArk just-in-time elevation, four-hour maximum; privileged access workstations mandatory; break-glass sealed, alerted on every use and reconciled within one business day; session recording retained 12 months. | J5: 5 | K5: 4 | L5: =J5*K5 -> 20 | M5: =IF(L5>=16,"Critical",IF(L5>=10,"High",IF(L5>=5,"Moderate","Low"))) -> Critical | N5: No Aldridge occurrence. Inherent L4 reflects the frequency of cloud credential compromise in published breach reporting. Residual L1 reflects dual custody and the absence of standing privilege. | O5: Strong | P5: 5 | Q5: 1 | R5: =P5*Q5 -> 5 | S5: =IF(R5>=16,"Critical",IF(R5>=10,"High",IF(R5>=5,"Moderate","Low"))) -> Moderate | T5: 9 | U5: =IF(R5<=T5,"Within","EXCEEDS") -> Within | V5: Tolerate | W5: Sanjay Mehta | X5: n/a | Y5: =IF(S5="Critical","Board Audit Committee",IF(S5="High","Executive Risk Committee",IF(S5="Moderate","CISO","Asset owner"))) -> CISO
A6: R-03 | B6: Cardholder data exfiltrated from the cardholder data environment | C6: A-02, A-01 | D6: TA-01 | E6: Organised criminal group | F6: Data confidentiality | G6: Extraction of stored account data following compromise of a CDE component | H6: The CDE remains a high-value target notwithstanding tokenisation. | I6: Tokenisation of stored account data; field-level encryption with customer-managed keys; network segregation validated annually by the QSA; DLP tuned to cardholder data patterns; monthly access recertification; comprehensive logging to Splunk. | J6: 5 | K6: 3 | L6: =J6*K6 -> 15 | M6: =IF(L6>=16,"Critical",IF(L6>=10,"High",IF(L6>=5,"Moderate","Low"))) -> High | N6: No Aldridge occurrence in five years of PCI operation. Residual L1 supported by annual QSA validation of segmentation. | O6: Strong | P6: 5 | Q6: 1 | R6: =P6*Q6 -> 5 | S6: =IF(R6>=16,"Critical",IF(R6>=10,"High",IF(R6>=5,"Moderate","Low"))) -> Moderate | T6: 9 | U6: =IF(R6<=T6,"Within","EXCEEDS") -> Within | V6: Tolerate | W6: Oliver Trent | X6: n/a | Y6: =IF(S6="Critical","Board Audit Committee",IF(S6="High","Executive Risk Committee",IF(S6="Moderate","CISO","Asset owner"))) -> CISO
A7: R-04 | B7: Borrower personal data exposed through unregistered software as a service | C7: A-05, A-09, A-17 | D7: TA-10 | E7: Worker (non-malicious) | F7: Data confidentiality | G7: Upload or synchronisation of Restricted or Confidential data to an unassessed third-party application | H7: Approximately 40 SaaS applications are in use without registration, owner, classification, contract or assessment (W-04). Web filtering blocks malicious destinations but not unsanctioned services (A.8.23). DLP does not cover these channels (A.8.12). | I7: POL-01 section 3.6 prohibits unapproved services; CASB provides discovery but not inline enforcement; annual awareness training. | J7: 4 | K7: 4 | L7: =J7*K7 -> 16 | M7: =IF(L7>=16,"Critical",IF(L7>=10,"High",IF(L7>=5,"Moderate","Low"))) -> Critical | N7: Condition present: CASB discovery in August 2026 identified approximately 40 applications. L4 inherent reflects that the behaviour is occurring; residual L3 reflects partial detection without prevention. | O7: Limited | P7: 4 | Q7: 3 | R7: =P7*Q7 -> 12 | S7: =IF(R7>=16,"Critical",IF(R7>=10,"High",IF(R7>=5,"Moderate","Low"))) -> High | T7: 9 | U7: =IF(R7<=T7,"Within","EXCEEDS") -> EXCEEDS | V7: Treat | W7: Claire Bennett | X7: 30 Nov 2026 | Y7: =IF(S7="Critical","Board Audit Committee",IF(S7="High","Executive Risk Committee",IF(S7="Moderate","CISO","Asset owner"))) -> Executive Risk Committee
A8: R-05 | B8: Identifiable borrower data retained beyond its lawful retention period | C8: A-09, A-05 | D8: TA-10 | E8: Internal process failure | F8: Regulatory compliance | G8: Continued storage of identifiable personal data after the purpose for processing has been fulfilled | H8: SCH-01 is published but not technically enforced. No automated deletion at end of retention. The condition is present and ongoing, not prospective (W-09). | I8: Records Retention Schedule published; legal hold process operated by the General Counsel; access control and encryption applied to the data at rest. | J8: 4 | K8: 5 | L8: =J8*K8 -> 20 | M8: =IF(L8>=16,"Critical",IF(L8>=10,"High",IF(L8>=5,"Moderate","Low"))) -> Critical | N8: Condition present and confirmed by inspection of the Snowflake estate. L5 is not an estimate; the non-compliance exists. | O8: Ineffective | P8: 4 | Q8: 5 | R8: =P8*Q8 -> 20 | S8: =IF(R8>=16,"Critical",IF(R8>=10,"High",IF(R8>=5,"Moderate","Low"))) -> Critical | T8: 9 | U8: =IF(R8<=T8,"Within","EXCEEDS") -> EXCEEDS | V8: Treat | W8: Claire Bennett | X8: 31 Mar 2027 | Y8: =IF(S8="Critical","Board Audit Committee",IF(S8="High","Executive Risk Committee",IF(S8="Moderate","CISO","Asset owner"))) -> Board Audit Committee
A9: R-06 | B9: Malicious activity in Aldridge Credit servicing goes undetected | C9: A-04, A-05 | D9: TA-05 | E9: External attacker or malicious insider | F9: Data confidentiality | G9: Unauthorised access to or manipulation of borrower servicing data that is neither detected nor reconstructable | H9: Approximately 15% of the Credit servicing estate does not ship logs to Splunk (W-10). Detection content for that estate is thin and unmapped to any threat framework. | I9: Perimeter and identity controls apply equally to this estate; EDR deployed; access recertification quarterly. | J9: 4 | K9: 4 | L9: =J9*K9 -> 16 | M9: =IF(L9>=16,"Critical",IF(L9>=10,"High",IF(L9>=5,"Moderate","Low"))) -> Critical | N9: Internal: 15% logging gap confirmed by reconciliation of the asset register to Splunk sources. No detection means occurrence cannot be excluded. | O9: Limited | P9: 4 | Q9: 3 | R9: =P9*Q9 -> 12 | S9: =IF(R9>=16,"Critical",IF(R9>=10,"High",IF(R9>=5,"Moderate","Low"))) -> High | T9: 9 | U9: =IF(R9<=T9,"Within","EXCEEDS") -> EXCEEDS | V9: Treat | W9: Tomas Vidal | X9: 31 Jan 2027 | Y9: =IF(S9="Critical","Board Audit Committee",IF(S9="High","Executive Risk Committee",IF(S9="Moderate","CISO","Asset owner"))) -> Executive Risk Committee
A10: R-07 | B10: Compromise of Northgate Analytics exposes data in the authorisation path | C10: A-10, A-01 | D10: TA-06 | E10: External attacker via supplier | F10: Data confidentiality | G10: Breach of a Tier 1 supplier receiving Restricted data synchronously during payment authorisation | H10: Last assessed October 2024, twenty-three months ago (W-08). Contract predates 2023 and lacks the current security schedule, including the 24-hour notification obligation. Subcontractors are undisclosed (A.5.21). | I10: Data shared is truncated and tokenised where possible; mutually authenticated integration; network path restricted; supplier holds a current SOC 2 report from 2024. | J10: 5 | K10: 4 | L10: =J10*K10 -> 20 | M10: =IF(L10>=16,"Critical",IF(L10>=10,"High",IF(L10>=5,"Moderate","Low"))) -> Critical | N10: Sector data on third-party breach frequency, adjusted upward for a supplier unassessed for 23 months with no notification obligation. | O10: Limited | P10: 5 | Q10: 3 | R10: =P10*Q10 -> 15 | S10: =IF(R10>=16,"Critical",IF(R10>=10,"High",IF(R10>=5,"Moderate","Low"))) -> High | T10: 9 | U10: =IF(R10<=T10,"Within","EXCEEDS") -> EXCEEDS | V10: Treat | W10: Elena Petrova | X10: 31 Jan 2027 | Y10: =IF(S10="Critical","Board Audit Committee",IF(S10="High","Executive Risk Committee",IF(S10="Moderate","CISO","Asset owner"))) -> Executive Risk Committee
A11: R-08 | B11: Northgate Analytics outage suspends payment authorisation | C11: A-10, A-01 | D11: TA-10 | E11: Supplier failure | F11: Third-party concentration | G11: Loss of the fraud decisioning service during trading hours | H11: Single supplier in a synchronous critical path with no assessed alternative. No documented exit plan, contrary to the risk appetite statement for Tier 1 concentration. | I11: Rules-based fallback scoring engaged automatically on supplier timeout, with tightened velocity limits while active; contractual availability commitment; status monitoring with alerting. | J11: 5 | K11: 3 | L11: =J11*K11 -> 15 | M11: =IF(L11>=16,"Critical",IF(L11>=10,"High",IF(L11>=5,"Moderate","Low"))) -> High | N11: Supplier availability history: two degradations in 24 months, both under 30 minutes, both absorbed by the fallback engine. | O11: Effective | P11: 4 | Q11: 2 | R11: =P11*Q11 -> 8 | S11: =IF(R11>=16,"Critical",IF(R11>=10,"High",IF(R11>=5,"Moderate","Low"))) -> Moderate | T11: 15 | U11: =IF(R11<=T11,"Within","EXCEEDS") -> Within | V11: Treat | W11: Oliver Trent | X11: 30 Jun 2027 | Y11: =IF(S11="Critical","Board Audit Committee",IF(S11="High","Executive Risk Committee",IF(S11="Moderate","CISO","Asset owner"))) -> CISO
A12: R-09 | B12: Restricted data resides with undisclosed fourth parties | C12: A-05, A-10 | D12: TA-06 | E12: Supplier subcontracting | F12: Regulatory compliance | G12: Onward transfer of Aldridge data to subcontractors that have not been identified, assessed or contractually bound | H12: No subcontractor disclosure requirement in the questionnaire or in contracts. Aldridge cannot state where Restricted data ultimately resides, including whether it leaves the UK or US (A.5.21). | I12: First-tier contracts include confidentiality terms; UK transfers governed by documented mechanisms for known flows only. | J12: 3 | K12: 4 | L12: =J12*K12 -> 12 | M12: =IF(L12>=16,"Critical",IF(L12>=10,"High",IF(L12>=5,"Moderate","Low"))) -> High | N12: Condition present: the chain is unmapped, so onward transfer cannot be excluded and is likely given standard SaaS architecture. | O12: Ineffective | P12: 3 | Q12: 4 | R12: =P12*Q12 -> 12 | S12: =IF(R12>=16,"Critical",IF(R12>=10,"High",IF(R12>=5,"Moderate","Low"))) -> High | T12: 9 | U12: =IF(R12<=T12,"Within","EXCEEDS") -> EXCEEDS | V12: Treat | W12: Elena Petrova | X12: 31 Mar 2027 | Y12: =IF(S12="Critical","Board Audit Committee",IF(S12="High","Executive Risk Committee",IF(S12="Moderate","CISO","Asset owner"))) -> Executive Risk Committee
A13: R-10 | B13: Offshore support agent exfiltrates customer data | C13: A-04, A-07 | D13: TA-05 | E13: Malicious insider at supplier | F13: Data confidentiality | G13: Bulk copying or photography of customer records by a Meridian BPO agent during dispute handling | H13: Human access to Confidential data, with Restricted access on escalation, from a jurisdiction where Aldridge has no direct oversight. DLP does not extend to the supplier's environment. | I13: Access limited to named agents through a dedicated time-bound path; activity logged; contractual background screening obligation; access scoped to the case in hand. | J13: 4 | K13: 3 | L13: =J13*K13 -> 12 | M13: =IF(L13>=16,"Critical",IF(L13>=10,"High",IF(L13>=5,"Moderate","Low"))) -> High | N13: No Aldridge occurrence. Sector data on BPO insider incidents; adjusted for the volume of agents with Confidential access and the absence of DLP in the supplier environment. | O13: Limited | P13: 4 | Q13: 3 | R13: =P13*Q13 -> 12 | S13: =IF(R13>=16,"Critical",IF(R13>=10,"High",IF(R13>=5,"Moderate","Low"))) -> High | T13: 9 | U13: =IF(R13<=T13,"Within","EXCEEDS") -> EXCEEDS | V13: Treat | W13: Elena Petrova | X13: 31 Mar 2027 | Y13: =IF(S13="Critical","Board Audit Committee",IF(S13="High","Executive Risk Committee",IF(S13="Moderate","CISO","Asset owner"))) -> Executive Risk Committee
A14: R-11 | B14: Worker credentials phished and used for account takeover | C14: A-11, A-17 | D14: TA-04 | E14: External attacker | F14: Data confidentiality | G14: Credential harvesting through a targeted phishing campaign, followed by authenticated access | H14: 610 workers reachable by email. Most recent simulation click rate 14.2% with 4.6% credential submission. | I14: Universal MFA; phishing-resistant FIDO2 for all privileged access; SMS one-time passcodes not accepted for privileged access; mail filtering; Report Phishing button with 31% report rate and 11-minute median first report; conditional access on device posture. | J14: 4 | K14: 5 | L14: =J14*K14 -> 20 | M14: =IF(L14>=16,"Critical",IF(L14>=10,"High",IF(L14>=5,"Moderate","Low"))) -> Critical | N14: Internal: 14.2% simulation click rate and 4.6% credential submission across 610 workers, four campaigns per year. L5 inherent is directly evidenced. | O14: Strong | P14: 3 | Q14: 2 | R14: =P14*Q14 -> 6 | S14: =IF(R14>=16,"Critical",IF(R14>=10,"High",IF(R14>=5,"Moderate","Low"))) -> Moderate | T14: 9 | U14: =IF(R14<=T14,"Within","EXCEEDS") -> Within | V14: Tolerate | W14: Ruth Nakamura | X14: n/a | Y14: =IF(S14="Critical","Board Audit Committee",IF(S14="High","Executive Risk Committee",IF(S14="Moderate","CISO","Asset owner"))) -> CISO
A15: R-12 | B15: Untrained population raises susceptibility to social engineering | C15: A-17, A-20 | D15: TA-04 | E15: External attacker | F15: Data confidentiality | G15: Successful manipulation of a worker who has not completed security training | H15: Training completion is 91%, with the residual 9% concentrated in Sales and the London office (W-14). Forty-seven repeat clickers have received no targeted intervention (W-15). | I15: Annual training platform in place; induction training required before access is granted; quarterly phishing simulation. | J15: 3 | K15: 4 | L15: =J15*K15 -> 12 | M15: =IF(L15>=16,"Critical",IF(L15>=10,"High",IF(L15>=5,"Moderate","Low"))) -> High | N15: Internal: 91% training completion; 47 repeat clickers across the last four campaigns. | O15: Limited | P15: 3 | Q15: 3 | R15: =P15*Q15 -> 9 | S15: =IF(R15>=16,"Critical",IF(R15>=10,"High",IF(R15>=5,"Moderate","Low"))) -> Moderate | T15: 9 | U15: =IF(R15<=T15,"Within","EXCEEDS") -> Within | V15: Treat | W15: Helen Achebe-Ward | X15: 31 Mar 2027 | Y15: =IF(S15="Critical","Board Audit Committee",IF(S15="High","Executive Risk Committee",IF(S15="Moderate","CISO","Asset owner"))) -> CISO
... A58: R-55 | B58: Compliance evidence cannot be produced on demand at examination or audit | C58: ISMS | D58: TA-10 | E58: Internal process failure (TA-10) | F58: Regulatory compliance | G58: A regulator, certification body or customer requests evidence that exists but cannot be located, versioned or attested within the time allowed | H58: Policies, exceptions, risks, control evidence and access review records are held across five uncontrolled spreadsheets with no version control or approval record (W-13). | I58: Evidence does substantively exist; the security team can assemble it with effort; PCI evidence production is mature and separately organised. | J58: 3 | K58: 4 | L58: =J58*K58 -> 12 | M58: =IF(L58>=16,"Critical",IF(L58>=10,"High",IF(L58>=5,"Moderate","Low"))) -> High | N58: Condition present: five uncontrolled spreadsheets. Likelihood reflects the probability of a demand arriving within the period before the GRC platform is implemented. | O58: Limited | P58: 3 | Q58: 3 | R58: =P58*Q58 -> 9 | S58: =IF(R58>=16,"Critical",IF(R58>=10,"High",IF(R58>=5,"Moderate","Low"))) -> Moderate | T58: 9 | U58: =IF(R58<=T58,"Within","EXCEEDS") -> Within | V58: Treat | W58: Chidi Eze | X58: 31 Dec 2026 | Y58: =IF(S58="Critical","Board Audit Committee",IF(S58="High","Executive Risk Committee",IF(S58="Moderate","CISO","Asset owner"))) -> CISO

Sheet Risk Treatment Plan
A1: Risk Treatment Plan
A2: Satisfies ISO/IEC 27001 clause 6.1.3(e) and (f). Yellow cells are signature blocks to be completed by the named risk owner.
A3: Risk ID | B3: Risk | C3: Res. rating | D3: Appetite test | E3: Treatment option | F3: Treatment action | G3: Action owner | H3: Target date | I3: Risk owner (accountable executive) | J3: Acceptance authority required | K3: Risk owner approval — signature | L3: Date approved
A4: R-01 | B4: Ransomware encrypts production estate and backups | C4: ='Risk Register'!S4 -> High | D4: ='Risk Register'!U4 -> EXCEEDS | E4: ='Risk Register'!V4 -> Treat | F4: Per remediation actions in AFT-ISMS-GAP-01 and the findings referenced at column Y of the register. Treatment target: residual within the tolerance at column T. | G4: ='Risk Register'!W4 -> Sanjay Mehta | H4: ='Risk Register'!X4 -> 31 Mar 2027 | I4: ='Risk Register'!W4 -> Sanjay Mehta | J4: ='Risk Register'!Y4 -> Executive Risk Committee
A5: R-02 | B5: Compromise of cloud control-plane credentials | C5: ='Risk Register'!S5 -> Moderate | D5: ='Risk Register'!U5 -> Within | E5: ='Risk Register'!V5 -> Tolerate | F5: No further treatment. Existing controls assessed as sufficient; residual accepted at the authority shown. | G5: ='Risk Register'!W5 -> Sanjay Mehta | H5: ='Risk Register'!X5 -> n/a | I5: ='Risk Register'!W5 -> Sanjay Mehta | J5: ='Risk Register'!Y5 -> CISO
A6: R-03 | B6: Cardholder data exfiltrated from the cardholder data environment | C6: ='Risk Register'!S6 -> Moderate | D6: ='Risk Register'!U6 -> Within | E6: ='Risk Register'!V6 -> Tolerate | F6: No further treatment. Existing controls assessed as sufficient; residual accepted at the authority shown. | G6: ='Risk Register'!W6 -> Oliver Trent | H6: ='Risk Register'!X6 -> n/a | I6: ='Risk Register'!W6 -> Oliver Trent | J6: ='Risk Register'!Y6 -> CISO
A7: R-04 | B7: Borrower personal data exposed through unregistered software as a service | C7: ='Risk Register'!S7 -> High | D7: ='Risk Register'!U7 -> EXCEEDS | E7: ='Risk Register'!V7 -> Treat | F7: Per remediation actions in AFT-ISMS-GAP-01 and the findings referenced at column Y of the register. Treatment target: residual within the tolerance at column T. | G7: ='Risk Register'!W7 -> Claire Bennett | H7: ='Risk Register'!X7 -> 30 Nov 2026 | I7: ='Risk Register'!W7 -> Claire Bennett | J7: ='Risk Register'!Y7 -> Executive Risk Committee
A8: R-05 | B8: Identifiable borrower data retained beyond its lawful retention period | C8: ='Risk Register'!S8 -> Critical | D8: ='Risk Register'!U8 -> EXCEEDS | E8: ='Risk Register'!V8 -> Treat | F8: Per remediation actions in AFT-ISMS-GAP-01 and the findings referenced at column Y of the register. Treatment target: residual within the tolerance at column T. | G8: ='Risk Register'!W8 -> Claire Bennett | H8: ='Risk Register'!X8 -> 31 Mar 2027 | I8: ='Risk Register'!W8 -> Claire Bennett | J8: ='Risk Register'!Y8 -> Board Audit Committee
A9: R-06 | B9: Malicious activity in Aldridge Credit servicing goes undetected | C9: ='Risk Register'!S9 -> High | D9: ='Risk Register'!U9 -> EXCEEDS | E9: ='Risk Register'!V9 -> Treat | F9: Per remediation actions in AFT-ISMS-GAP-01 and the findings referenced at column Y of the register. Treatment target: residual within the tolerance at column T. | G9: ='Risk Register'!W9 -> Tomas Vidal | H9: ='Risk Register'!X9 -> 31 Jan 2027 | I9: ='Risk Register'!W9 -> Tomas Vidal | J9: ='Risk Register'!Y9 -> Executive Risk Committee
A10: R-07 | B10: Compromise of Northgate Analytics exposes data in the authorisation path | C10: ='Risk Register'!S10 -> High | D10: ='Risk Register'!U10 -> EXCEEDS | E10: ='Risk Register'!V10 -> Treat | F10: Per remediation actions in AFT-ISMS-GAP-01 and the findings referenced at column Y of the register. Treatment target: residual within the tolerance at column T. | G10: ='Risk Register'!W10 -> Elena Petrova | H10: ='Risk Register'!X10 -> 31 Jan 2027 | I10: ='Risk Register'!W10 -> Elena Petrova | J10: ='Risk Register'!Y10 -> Executive Risk Committee
A11: R-08 | B11: Northgate Analytics outage suspends payment authorisation | C11: ='Risk Register'!S11 -> Moderate | D11: ='Risk Register'!U11 -> Within | E11: ='Risk Register'!V11 -> Treat | F11: Per remediation actions in AFT-ISMS-GAP-01 and the findings referenced at column Y of the register. Treatment target: residual within the tolerance at column T. | G11: ='Risk Register'!W11 -> Oliver Trent | H11: ='Risk Register'!X11 -> 30 Jun 2027 | I11: ='Risk Register'!W11 -> Oliver Trent | J11: ='Risk Register'!Y11 -> CISO
A12: R-09 | B12: Restricted data resides with undisclosed fourth parties | C12: ='Risk Register'!S12 -> High | D12: ='Risk Register'!U12 -> EXCEEDS | E12: ='Risk Register'!V12 -> Treat | F12: Per remediation actions in AFT-ISMS-GAP-01 and the findings referenced at column Y of the register. Treatment target: residual within the tolerance at column T. | G12: ='Risk Register'!W12 -> Elena Petrova | H12: ='Risk Register'!X12 -> 31 Mar 2027 | I12: ='Risk Register'!W12 -> Elena Petrova | J12: ='Risk Register'!Y12 -> Executive Risk Committee
A13: R-10 | B13: Offshore support agent exfiltrates customer data | C13: ='Risk Register'!S13 -> High | D13: ='Risk Register'!U13 -> EXCEEDS | E13: ='Risk Register'!V13 -> Treat | F13: Per remediation actions in AFT-ISMS-GAP-01 and the findings referenced at column Y of the register. Treatment target: residual within the tolerance at column T. | G13: ='Risk Register'!W13 -> Elena Petrova | H13: ='Risk Register'!X13 -> 31 Mar 2027 | I13: ='Risk Register'!W13 -> Elena Petrova | J13: ='Risk Register'!Y13 -> Executive Risk Committee
A14: R-11 | B14: Worker credentials phished and used for account takeover | C14: ='Risk Register'!S14 -> Moderate | D14: ='Risk Register'!U14 -> Within | E14: ='Risk Register'!V14 -> Tolerate | F14: No further treatment. Existing controls assessed as sufficient; residual accepted at the authority shown. | G14: ='Risk Register'!W14 -> Ruth Nakamura | H14: ='Risk Register'!X14 -> n/a | I14: ='Risk Register'!W14 -> Ruth Nakamura | J14: ='Risk Register'!Y14 -> CISO
A15: R-12 | B15: Untrained population raises susceptibility to social engineering | C15: ='Risk Register'!S15 -> Moderate | D15: ='Risk Register'!U15 -> Within | E15: ='Risk Register'!V15 -> Treat | F15: Per remediation actions in AFT-ISMS-GAP-01 and the findings referenced at column Y of the register. Treatment target: residual within the tolerance at column T. | G15: ='Risk Register'!W15 -> Helen Achebe-Ward | H15: ='Risk Register'!X15 -> 31 Mar 2027 | I15: ='Risk Register'!W15 -> Helen Achebe-Ward | J15: ='Risk Register'!Y15 -> CISO
... A58: R-55 | B58: Compliance evidence cannot be produced on demand at examination or audit | C58: ='Risk Register'!S58 -> Moderate | D58: ='Risk Register'!U58 -> Within | E58: ='Risk Register'!V58 -> Treat | F58: Per remediation actions in AFT-ISMS-GAP-01 and the findings referenced at column Y of the register. Treatment target: residual within the tolerance at column T. | G58: ='Risk Register'!W58 -> Chidi Eze | H58: ='Risk Register'!X58 -> 31 Dec 2026 | I58: ='Risk Register'!W58 -> Chidi Eze | J58: ='Risk Register'!Y58 -> CISO
A60: Clause 6.1.3(f) requires the risk owner to approve the risk treatment plan and to accept the residual information security risk. The signature columns are unsigned. Until they are completed, the ISMS does not satisfy clause 6.1.3 irrespective of the quality of the assessment, and this is a certification-blocking condition. Acceptance authority in column J is the level at which the residual may be accepted per AFT-CTX-01 section 16; it does not replace the risk owner's own approval, which is required in every case.

Sheet Summary & Heat Map
A1: Risk Summary
A2: All counts are formulas driven by the Risk Register tab.
A4: RESIDUAL RISK PROFILE
A5: Rating | B5: Inherent | C5: Residual | D5: Movement
A6: Critical | B6: =COUNTIF('Risk Register'!$M$4:$M$58,A6) -> 13 | C6: =COUNTIF('Risk Register'!$S$4:$S$58,A6) -> 1 | D6: =C6-B6 -> -12
A7: High | B7: =COUNTIF('Risk Register'!$M$4:$M$58,A7) -> 35 | C7: =COUNTIF('Risk Register'!$S$4:$S$58,A7) -> 22 | D7: =C7-B7 -> -13
A8: Moderate | B8: =COUNTIF('Risk Register'!$M$4:$M$58,A8) -> 7 | C8: =COUNTIF('Risk Register'!$S$4:$S$58,A8) -> 31 | D8: =C8-B8 -> 24
A9: Low | B9: =COUNTIF('Risk Register'!$M$4:$M$58,A9) -> 0 | C9: =COUNTIF('Risk Register'!$S$4:$S$58,A9) -> 1 | D9: =C9-B9 -> 1
A10: Total risks | B10: =COUNTA('Risk Register'!$A$4:$A$58) -> 55
A12: APPETITE AND GOVERNANCE POSITION
A13: Risks exceeding appetite | B13: =COUNTIF('Risk Register'!$U$4:$U$58,"EXCEEDS") -> 23
A14: Risks within appetite | B14: =COUNTIF('Risk Register'!$U$4:$U$58,"Within") -> 32
A15: Requiring Board Audit Committee acceptance | B15: =COUNTIF('Risk Register'!$Y$4:$Y$58,"Board Audit Committee") -> 1
A16: Requiring Executive Risk Committee acceptance | B16: =COUNTIF('Risk Register'!$Y$4:$Y$58,"Executive Risk Committee") -> 22
A17: Treatment: Treat | B17: =COUNTIF('Risk Register'!$V$4:$V$58,"Treat") -> 43
A18: Treatment: Tolerate | B18: =COUNTIF('Risk Register'!$V$4:$V$58,"Tolerate") -> 12
A19: Risk owner approvals outstanding | B19: =COUNTA('Risk Register'!$A$4:$A$58)-COUNTA('Risk Treatment Plan'!$K$4:$K$58) -> 55
A21: RISKS BY THREAT SOURCE
A22: Threat source | B22: Risks | C22: Exceeding appetite
A23: TA-01 — Organised cybercriminal (extortion) | B23: =COUNTIF('Risk Register'!$D$4:$D$58,"TA-01") -> 2 | C23: =COUNTIFS('Risk Register'!$D$4:$D$58,"TA-01",'Risk Register'!$U$4:$U$58,"EXCEEDS") -> 1
A24: TA-02 — Payment fraud syndicate | B24: =COUNTIF('Risk Register'!$D$4:$D$58,"TA-02") -> 3 | C24: =COUNTIFS('Risk Register'!$D$4:$D$58,"TA-02",'Risk Register'!$U$4:$U$58,"EXCEEDS") -> 0
A25: TA-03 — Lending fraud ring | B25: =COUNTIF('Risk Register'!$D$4:$D$58,"TA-03") -> 1 | C25: =COUNTIFS('Risk Register'!$D$4:$D$58,"TA-03",'Risk Register'!$U$4:$U$58,"EXCEEDS") -> 1
A26: TA-04 — Initial access broker / phishing crew | B26: =COUNTIF('Risk Register'!$D$4:$D$58,"TA-04") -> 2 | C26: =COUNTIFS('Risk Register'!$D$4:$D$58,"TA-04",'Risk Register'!$U$4:$U$58,"EXCEEDS") -> 0
A27: TA-05 — Malicious or coerced insider | B27: =COUNTIF('Risk Register'!$D$4:$D$58,"TA-05") -> 5 | C27: =COUNTIFS('Risk Register'!$D$4:$D$58,"TA-05",'Risk Register'!$U$4:$U$58,"EXCEEDS") -> 2
A28: TA-06 — Supply chain / sub-processor | B28: =COUNTIF('Risk Register'!$D$4:$D$58,"TA-06") -> 6 | C28: =COUNTIFS('Risk Register'!$D$4:$D$58,"TA-06",'Risk Register'!$U$4:$U$58,"EXCEEDS") -> 3
A29: TA-07 — Hacktivist / DDoS extortion | B29: =COUNTIF('Risk Register'!$D$4:$D$58,"TA-07") -> 1 | C29: =COUNTIFS('Risk Register'!$D$4:$D$58,"TA-07",'Risk Register'!$U$4:$U$58,"EXCEEDS") -> 0
A30: TA-08 — State-aligned actor | B30: =COUNTIF('Risk Register'!$D$4:$D$58,"TA-08") -> 4 | C30: =COUNTIFS('Risk Register'!$D$4:$D$58,"TA-08",'Risk Register'!$U$4:$U$58,"EXCEEDS") -> 1
A31: TA-09 — Sanctions evader / money launderer | B31: =COUNTIF('Risk Register'!$D$4:$D$58,"TA-09") -> 2 | C31: =COUNTIFS('Risk Register'!$D$4:$D$58,"TA-09",'Risk Register'!$U$4:$U$58,"EXCEEDS") -> 2
A32: TA-10 — Non-adversarial | B32: =COUNTIF('Risk Register'!$D$4:$D$58,"TA-10") -> 29 | C32: =COUNTIFS('Risk Register'!$D$4:$D$58,"TA-10",'Risk Register'!$U$4:$U$58,"EXCEEDS") -> 13
A35: RESIDUAL HEAT MAP
A36: Impact ↓ / Likelihood → | B36: L1 | C36: L2 | D36: L3 | E36: L4 | F36: L5
A37: I5 | B37: =COUNTIFS('Risk Register'!$P$4:$P$58,5,'Risk Register'!$Q$4:$Q$58,1) -> 2 | C37: =COUNTIFS('Risk Register'!$P$4:$P$58,5,'Risk Register'!$Q$4:$Q$58,2) -> 6 | D37: =COUNTIFS('Risk Register'!$P$4:$P$58,5,'Risk Register'!$Q$4:$Q$58,3) -> 2 | E37: =COUNTIFS('Risk Register'!$P$4:$P$58,5,'Risk Register'!$Q$4:$Q$58,4) -> 0 | F37: =COUNTIFS('Risk Register'!$P$4:$P$58,5,'Risk Register'!$Q$4:$Q$58,5) -> 0
A38: I4 | B38: =COUNTIFS('Risk Register'!$P$4:$P$58,4,'Risk Register'!$Q$4:$Q$58,1) -> 1 | C38: =COUNTIFS('Risk Register'!$P$4:$P$58,4,'Risk Register'!$Q$4:$Q$58,2) -> 5 | D38: =COUNTIFS('Risk Register'!$P$4:$P$58,4,'Risk Register'!$Q$4:$Q$58,3) -> 12 | E38: =COUNTIFS('Risk Register'!$P$4:$P$58,4,'Risk Register'!$Q$4:$Q$58,4) -> 0 | F38: =COUNTIFS('Risk Register'!$P$4:$P$58,4,'Risk Register'!$Q$4:$Q$58,5) -> 1
A39: I3 | B39: =COUNTIFS('Risk Register'!$P$4:$P$58,3,'Risk Register'!$Q$4:$Q$58,1) -> 0 | C39: =COUNTIFS('Risk Register'!$P$4:$P$58,3,'Risk Register'!$Q$4:$Q$58,2) -> 6 | D39: =COUNTIFS('Risk Register'!$P$4:$P$58,3,'Risk Register'!$Q$4:$Q$58,3) -> 17 | E39: =COUNTIFS('Risk Register'!$P$4:$P$58,3,'Risk Register'!$Q$4:$Q$58,4) -> 2 | F39: =COUNTIFS('Risk Register'!$P$4:$P$58,3,'Risk Register'!$Q$4:$Q$58,5) -> 0
A40: I2 | B40: =COUNTIFS('Risk Register'!$P$4:$P$58,2,'Risk Register'!$Q$4:$Q$58,1) -> 0 | C40: =COUNTIFS('Risk Register'!$P$4:$P$58,2,'Risk Register'!$Q$4:$Q$58,2) -> 0 | D40: =COUNTIFS('Risk Register'!$P$4:$P$58,2,'Risk Register'!$Q$4:$Q$58,3) -> 1 | E40: =COUNTIFS('Risk Register'!$P$4:$P$58,2,'Risk Register'!$Q$4:$Q$58,4) -> 0 | F40: =COUNTIFS('Risk Register'!$P$4:$P$58,2,'Risk Register'!$Q$4:$Q$58,5) -> 0
A41: I1 | B41: =COUNTIFS('Risk Register'!$P$4:$P$58,1,'Risk Register'!$Q$4:$Q$58,1) -> 0 | C41: =COUNTIFS('Risk Register'!$P$4:$P$58,1,'Risk Register'!$Q$4:$Q$58,2) -> 0 | D41: =COUNTIFS('Risk Register'!$P$4:$P$58,1,'Risk Register'!$Q$4:$Q$58,3) -> 0 | E41: =COUNTIFS('Risk Register'!$P$4:$P$58,1,'Risk Register'!$Q$4:$Q$58,4) -> 0 | F41: =COUNTIFS('Risk Register'!$P$4:$P$58,1,'Risk Register'!$Q$4:$Q$58,5) -> 0
A44: GOVERNANCE OBSERVATION. A large number of risks sit outside appetite. That is a function of the appetite statement as much as of the control environment: AFT-CTX-01 section 7.4 sets an Averse appetite for both data confidentiality and regulatory compliance, capping acceptable residual at Moderate for the two categories that cover most of the register. An appetite that generates an exceedance list longer than the treatment programme can clear within the year is either aspirational or under-resourced, and the ERC should resolve which. The options are to fund treatment at the level the appetite implies, or to restate the appetite at a level the organisation is actually prepared to operate to. Carrying a permanent exceedance list is the worst of the three, because it normalises operating outside a stated appetite and devalues the escalation it is supposed to trigger.
